[{"defs":[{"pos":"n","trans":"会议；会期（session 的复数）"}],"pron":"/ ˈseʃnz /","word":"sessions"},{"defs":[{"pos":"n","trans":"（坚果可食用的）仁，核；玉米粒；（陈述、观点、计划等的）核心，要点；（某物的）极小一部分，微量；（计算机操作系统的）核心程序；（语言学）核心句"}],"pron":"/ ˈkɜːrnl /","word":"kernel"},{"defs":[{"pos":"n","trans":"乳房；（美）笨蛋；愚蠢的错误（boob 的复数）"},{"pos":"vi","trans":"犯可笑的错误（boob 的第三人称单数形式）"}],"pron":"/ buːbz /","word":"boobs"},{"defs":[{"pos":"n","trans":"[金融]股票；[贸易]存货；库存量（stock 的复数）"},{"pos":"v","trans":"采购；有……的存货；贮存（stock 的第三人称单数）"},{"pos":"n","trans":"（Stocks）人名；（英）斯托克斯；（德）施托克斯"}],"pron":"/ stɑːks /","word":"stocks"},{"defs":[{"pos":"n","trans":"[贸易]买主；买方市场；采购者；购货者（buyer 的复数）"},{"pos":"n","trans":"（Buyers）人名；（英）拜尔斯"}],"pron":"/ ˈbaɪərz /","word":"buyers"},{"defs":[{"pos":"n","trans":"学术期刊（journal 的复数）；日记；日记账"}],"pron":"/ ˈdʒɜːrnl /","word":"journals"},{"defs":[{"pos":"adj","trans":"灰色的；苍白的；灰白头发的；阴郁的"},{"pos":"n","trans":"灰色；暗淡的光线"},{"pos":"vi","trans":"成为灰色或灰白"},{"pos":"vt","trans":"使成灰色或灰白"},{"pos":"n","trans":"（Gray）人名；（意）格拉伊；（英、法、葡、瑞典）格雷"}],"pron":"/ ɡreɪ /","word":"gray"},{"defs":[{"pos":"n","trans":"目录，目录册；一系列，一连串（坏事情）；<美>大学情况一览"},{"pos":"v","trans":"列入目录，编入目录；列举，记载"}],"pron":"/ ˈkætəlɔːɡ /","word":"catalogue"},{"defs":[{"pos":"abbr","trans":"艺电公司（Electronic Arts）"},{"pos":"n","trans":"（Ea）人名；（柬）叶；（刚（金））埃亚"}],"pron":"/ ,i 'e /","word":"ea"},{"defs":[{"pos":"n","trans":"詹尼弗（女子名）"}],"pron":"/ ˈdʒenəfər /","word":"jennifer"},{"defs":[{"pos":"n","trans":"安东尼奥（男名）"}],"pron":"/ ænˈtoʊnioʊ /","word":"antonio"},{"defs":[{"pos":"adj","trans":"引起强烈感情的，气氛紧张的；充电的，带电的"},{"pos":"v","trans":"充电；使……承担责任；控告，指控（charge 的和过去式和过去分词形式）"}],"pron":"/ tʃɑːrdʒd /","word":"charged"},{"defs":[{"pos":"adj","trans":"宽广的，宽阔的；……宽；咧开嘴的；广泛的，普遍的；大致的，概括的；明确的，明显的；粗俗滑稽的；口音重的"},{"pos":"n","trans":"<美>女人，娘儿们；宽阔部分"},{"pos":"adv","trans":"宽阔地"},{"pos":"","trans":"【名】 （Broad）（英、德）布罗德（人名）"}],"pron":"/ brɔːd /","word":"broad"},{"defs":[{"pos":"n","trans":"台湾"}],"pron":"/ ˈtaɪˈwɑːn /","word":"taiwan"},{"defs":[{"pos":"comb","trans":"表示“水，波浪”"}],"pron":"/ ,ju ɛn 'di /","word":"und"},{"defs":[{"pos":"vt","trans":"选择（choose 的过去分词）"},{"pos":"adj","trans":"挑选出来的，精选的"}],"pron":"/ ˈtʃoʊzn /","word":"chosen"},{"defs":[{"pos":"n","trans":"试样唱片；示范；（产品的）样品；<英，非正式>示威游行"},{"pos":"v","trans":"演示，示范"},{"pos":"","trans":"【名】 （Demo）（意、阿尔巴）德莫（人名）"}],"pron":"/ ˈdemoʊ /","word":"demo"},{"defs":[{"pos":"","trans":"希腊（欧洲南部国家）"}],"pron":"/ ɡriːs /","word":"greece"},{"defs":[{"pos":"abbr","trans":"水平规， 水准仪（Level Gauge ）"},{"pos":"","trans":"直线发生器， 矢量发生器（Line Generator）"}],"word":"lg"},{"defs":[{"pos":"adj","trans":"瑞士的；瑞士人的；瑞士风格的"},{"pos":"n","trans":"瑞士人；瑞士腔调"}],"pron":"/ swɪs /","word":"swiss"},{"defs":[{"pos":"n","trans":"莎拉（女子名）；萨拉（《圣经》中的人物）"}],"pron":"/ ˈserə /","word":"sarah"},{"defs":[{"pos":"n","trans":"克拉克（男子名）"},{"pos":"n","trans":"（Clark）人名；（瑞典、葡、西、芬、斐、意、德、匈、英、土）克拉克"}],"pron":"/ klɑ:k /","word":"clark"},{"defs":[{"pos":"n","trans":"劳动；工作；劳工；分娩"},{"pos":"vi","trans":"劳动；努力；苦干"},{"pos":"vt","trans":"详细分析；使厌烦"},{"pos":"n","trans":"（Labor）人名；（德、塞、法）拉博尔；（英）拉博"}],"pron":"/ ˈleɪbər /","word":"labor"},{"defs":[{"pos":"v","trans":"厌恶，不喜欢；仇恨，憎恨；（表示不愿说某事，或客气地请求）不愿，不想"},{"pos":"n","trans":"憎恶，憎恨；<非正式> 所憎恶的人（或事物）；<非正式>所憎恶的人（或事物）"},{"pos":"","trans":"【名】 （Hate）（法）阿特（人名）"}],"pron":"/ heɪt /","word":"hate"},{"defs":[{"pos":"n","trans":"（火车、公共汽车或船的）终点站；航空终点站，航站楼；电脑终端；（电路的）端子，线接头；<英>晚期病人；（石油，天然气的）集散站；（建筑）界标，端饰，胸像柱"},{"pos":"adj","trans":"（疾病） 致命的，不治的，晚期的；（病状）已达晚期的；逐步衰亡的，越来越糟的；终端的，末端的；极度的，极其的；学期的，期末的，按期的；（运输）终点（站）的；（动）末端的，远端的；（植）（花朵等）顶生的"}],"pron":"/ ˈtɜːrmɪn(ə)l /","word":"terminal"},{"defs":[{"pos":"n","trans":"出版商，出版公司；出版社（publisher 的复数）"}],"pron":"/ ˈpʌblɪʃər /","word":"publishers"},{"defs":[{"pos":"n","trans":"夜；晚上（night 的复数形式）"},{"pos":"adv","trans":"每晚；在夜间"}],"pron":"/ naɪts /","word":"nights"},{"defs":[{"pos":"n","trans":"代表（on behalf of）；因为，为了……的利益（in/on behalf of）；就……而言，在……一方（on behalf of）"}],"pron":"/ bɪˈhæf /","word":"behalf"},{"defs":[{"pos":"adj","trans":"加勒比海的；加勒比人的；加勒比语的"},{"pos":"n","trans":"加勒比海"}],"pron":"/ ˌkærɪˈbiːənˌkəˈrɪbiən /","word":"caribbean"},{"defs":[{"pos":"n","trans":"液体，液态物；流音"},{"pos":"adj","trans":"液态的，液化的；（资金等）流动的，易变为现金的；流畅自如的，舒展的；明亮的，清澈的；清脆的，流畅的；（市场）活跃的；液态的，液化的;（资金等）流动的，易变为现金的"}],"pron":"/ ˈlɪkwɪd /","word":"liquid"},{"defs":[{"pos":"n","trans":"稻；米饭"},{"pos":"vt","trans":"把……捣成米糊状"},{"pos":"n","trans":"（Rice）人名；（瑞典）里瑟；（塞）里采；（英）赖斯"}],"pron":"/ raɪs /","word":"rice"},{"defs":[{"pos":"n","trans":"内布拉斯加州"}],"pron":"/ nəˈbræskə /","word":"nebraska"},{"defs":[{"pos":"n","trans":"环形，环状物；循环胶片，循环磁带；（程序中）一套重复的指令；回线，回路；<英>（铁道或公路的）环线；<美，非正式>大环（指美国芝加哥市的商业中心）；<英>（可改道的）会车线；翻筋斗（一种飞行特技）；（滑冰）单刃转圈"},{"pos":"v","trans":"使成环，使绕成圈；成环形运动；播放一卷磁带，放一卷电影胶片，执行计算机指令"},{"pos":"","trans":"【名】 （Loop）（美、丹）劳鄱（人名）"}],"pron":"/ luːp /","word":"loop"},{"defs":[{"pos":"n","trans":"薪金，薪水"},{"pos":"v","trans":"<古> 给……薪金"}],"pron":"/ ˈsæləri /","word":"salary"},{"defs":[{"pos":"n","trans":"保留，保护；（房间，座位等的）预订；（美国印第安人的）居留地，保留地；（野生动物）保护区；<法律>（财产转让的）权益保留；圣餐保留（指弥撒完毕后部分圣餐留给病人或作为礼拜之用）；存疑，保留；（罗马天主教高级圣职人员的）赦罪权的保留；（教皇的）任命权保留"}],"pron":"/ ˌrezərˈveɪʃn /","word":"reservation"},{"defs":[{"pos":"n","trans":"[食品] 食品"}],"pron":"/ fuːdz /","word":"foods"},{"defs":[{"pos":"n","trans":"美食家；美食家"},{"pos":"adj","trans":"（食物）美味的；提供美食的"}],"pron":"/ ˈɡʊrmeɪ /","word":"gourmet"},{"defs":[{"pos":"n","trans":"卫兵，警卫；看守，保卫，警戒；列车长；保护装置；（英国的）禁卫军；（篮球）后卫；（拳击运动员的）防御姿势"},{"pos":"v","trans":"守卫，保卫；看守，监视；警惕，防范；保护，维护"},{"pos":"","trans":"【名】 （Guard）（英）格尔德（人名）"}],"pron":"/ ɡɑːrd /","word":"guard"},{"defs":[{"pos":"adv","trans":"正确地，适当地；得体地，恰当地；实际上，严格地说；彻底地，完全地"}],"pron":"/ ˈprɑːpərli /","word":"properly"},{"defs":[{"pos":"n","trans":"奥尔良（法国城市）"}],"pron":"/ ˈɔːrlənz /","word":"orleans"},{"defs":[{"pos":"n","trans":"（钱、时间或其他资源的）节约，节省；储蓄金，存款；<法律> 保留，例外；存钱"},{"pos":"adj","trans":"节约的，节省的；节俭的，省钱的"},{"pos":"prep","trans":"除了，除……外"},{"pos":"","trans":"【名】 （Saving）人名，（瑞典）萨温"},{"pos":"v","trans":"救援，挽救；节省；保存（save 的现在分词形式）"}],"pron":"/ ˈseɪvɪŋ /","word":"saving"},{"defs":[{"pos":"abbr","trans":"（美）全国橄榄球联盟（National Football League）"}],"pron":"/ ˌen ef ˈel /","word":"nfl"},{"defs":[{"pos":"adj","trans":"剩下的，遗留的；尚未使用、解决的；尚未发生的"},{"pos":"v","trans":"保持不变；遗留；尚待处理（remain 的现在分词）"}],"pron":"/ rɪˈmeɪnɪŋ /","word":"remaining"},{"defs":[{"pos":"n","trans":"帝国；大企业，大集团；君权，最高统治权"},{"pos":"","trans":"【名】 （Empire）（法）昂皮尔（人名）"}],"pron":"/ ˈempaɪər /","word":"empire"},{"defs":[{"pos":"v","trans":"恢复（职位），回到（座位）；继续说，接着说；概述；（中断后）重新开始，继续"},{"pos":"n","trans":"梗概，摘要（résumé或resumé）；<美>简历，履历（résumé或resumé）"}],"pron":"/ rɪˈzuːm /","word":"resume"},{"defs":[{"pos":"n","trans":"二十；二十年代"},{"pos":"num","trans":"二十"},{"pos":"adj","trans":"二十的"}],"pron":"/ ˈtwenti /","word":"twenty"},{"defs":[{"pos":"adv","trans":"最近；重新；以新的方式"}],"pron":"/ ˈnuːli /","word":"newly"},{"defs":[{"pos":"v","trans":"提升，举起；（使）直立，站立；建造，树立（纪念碑等）；增加，提高（数量、水平等）；筹集，筹募；召集，征募（尤指士兵）；提及（某事）；引起，使出现；饲养，种植；抚养，养育； 使积方，使自乘……次；比（对手）多下赌注； 打捞（船只）；使（面包）发酵；使复活；（暂时）终止，解除；（通过无线电或电话）与……取得联系；开具（发货单或其他单据）；把（动物）从窝里赶出；（海上人员）驶近能看见（陆地或其他船只）的地方；（免疫）刺激（抗血清、抗体等的）生成"},{"pos":"n","trans":"<美>加薪；（扑克牌或勃莱格牌用语）赌注加码；（举重）（持杠铃时的）提，举；上升"},{"pos":"","trans":"【名】 （Raise）（意、法、英、美）雷兹（人名）"}],"pron":"/ reɪz /","word":"raise"},{"defs":[{"pos":"v","trans":"使做好准备，把……预备好；（为……）做好准备；预备（饭菜），做（饭）；配制（药品或化学制品）；乐意做（be prepared to do sth.）；（在和弦中）预备（不和谐音）"}],"pron":"/ prɪˈper /","word":"prepare"},{"defs":[{"pos":"n","trans":"化身（印度教中化作人形或兽形的神）；（人或思想的）化身，体现；（在电脑游戏或网络中代表使用者的）图标，头像；<正式>代表人物；化身（印度教中化作人形或兽形的神）"}],"pron":"/ ˈævətɑːr /","word":"avatar"},{"defs":[{"pos":"n","trans":"盖理"}],"word":"gary"},{"defs":[{"pos":"v","trans":"依赖；信任（depend 的 ing 形式）"}],"pron":"/ dɪˈpendɪŋ /","word":"depending"},{"defs":[{"pos":"adj","trans":"非法的，违法的；违规的"},{"pos":"n","trans":"非法移民，非法劳工"}],"pron":"/ ɪˈliːɡl /","word":"illegal"},{"defs":[{"pos":"n","trans":"扩大，扩张；扩充，展开；扩张物；膨胀"}],"pron":"/ ɪkˈspænʃn /","word":"expansion"},{"defs":[{"pos":"v","trans":"（使）不同，（使）呈现差异；（根据情况而）变化，改变；改变，使……变化；变奏"},{"pos":"","trans":"【名】 （Vary）（英、法、罗、柬）瓦里（人名）"}],"pron":"/ ˈveri /","word":"vary"},{"defs":[{"pos":"n","trans":"数百"},{"pos":"","trans":"百"},{"pos":"","trans":"百分之百"},{"pos":"","trans":"成百上千"}],"pron":"/ ˈhʌndrədz /","word":"hundreds"},{"defs":[{"pos":"n","trans":"罗马（意大利首都）"}],"pron":"/ roʊm /","word":"rome"},{"defs":[{"pos":"adj","trans":"阿拉伯的"},{"pos":"n","trans":"阿拉伯人；阿拉伯马"}],"pron":"/ ˈærəb /","word":"arab"},{"defs":[{"pos":"n","trans":"林肯（美国第16任总统）；林肯（福特汽车厂出产的名牌豪华汽车）"}],"pron":"/ ˈlɪŋkən /","word":"lincoln"},{"defs":[{"pos":"v","trans":"帮助（help 的过去分词）"}],"pron":"/ helpt /","word":"helped"},{"defs":[{"pos":"adj","trans":"首要的，最好的；最早的，最初的"},{"pos":"n","trans":"总理，首相；（加拿大的）省总理，地方总理；（澳大利亚州或地区的）省长"}],"pron":"/ prɪˈmɪr /","word":"premier"},{"defs":[{"pos":"adv","trans":"在明天，在明日；（尤指不久的）将来"},{"pos":"n","trans":"明天，明日；未来"}],"pron":"/ təˈmɑːroʊ /","word":"tomorrow"},{"defs":[{"pos":"adj","trans":"已经购买的"},{"pos":"v","trans":"购买（purchase 的过去分词）"}],"pron":"/ 'pə:tʃəst /","word":"purchased"},{"defs":[{"pos":"n","trans":"（牛或羊等的）奶；奶汁，母乳；乳液（用于清洁或保护皮肤）；（椰子等植物的）白色汁液"},{"pos":"v","trans":"挤奶；榨取，勒索；充分利用；迎合（观众）；（动物，尤指母牛）产奶，出奶；从……抽取液汁（或毒液等）"},{"pos":"","trans":"【名】 （Milk）（英）米尔克（人名）"}],"pron":"/ mɪlk /","word":"milk"},{"defs":[{"pos":"v","trans":"影响（或决定）……的结果；断定，判定；使下决心；决定，选定；裁决，判决"}],"pron":"/ dɪˈsaɪd /","word":"decide"},{"defs":[{"pos":"n","trans":"许可，允许；同意，赞同；正式批准文件，批文"},{"pos":"v","trans":"赞同，准许，同意"},{"pos":"","trans":"【名】 （Consent）（美、法、荷）孔桑（人名）"}],"pron":"/ kənˈsent /","word":"consent"},{"defs":[{"pos":"n","trans":"剧本，戏剧；戏剧研究，戏剧艺术；戏剧性场面，戏剧性事件；激动，刺激"},{"pos":"","trans":"【名】 （Drama）（刚(金)）德拉马（人名）"}],"pron":"/ ˈdrɑːmə /","word":"drama"},{"defs":[{"pos":"adj","trans":"（指教授或讲师）客座的；访问的，参观的"},{"pos":"v","trans":"拜访；游览（某地）；探望（某人）；访问（网站）；（短暂地）作客（visit 的现在分词）"}],"pron":"/ ˈvɪzɪtɪŋ /","word":"visiting"},{"defs":[{"pos":"adj","trans":"表演的；履行的"},{"pos":"v","trans":"表演；履行（perform 的现在分词）"}],"pron":"/ pərˈfɔːrmɪŋ /","word":"performing"},{"defs":[{"pos":"adj","trans":"市中心的，商业区的"},{"pos":"adv","trans":"向（在）市中心，向（在）城镇商业中心区"},{"pos":"n","trans":"城镇的中心区，商业区，闹市区"}],"pron":"/ ˌdaʊnˈtaʊn /","word":"downtown"},{"defs":[{"pos":"n","trans":"（打字机或计算机的）键盘；（钢琴或风琴的）琴键；键盘乐器"},{"pos":"v","trans":"用键盘输入；用键盘操作"}],"pron":"/ ˈkiːbɔːrd /","word":"keyboard"},{"defs":[{"pos":"n","trans":"比赛，竞赛；争夺，竞争；争论，争执"},{"pos":"v","trans":"争辩，提出异议；争取赢得，角逐"}],"pron":"/ ˈkɑːntest /","word":"contest"},{"defs":[{"pos":"v","trans":"收集；收藏；聚集；聚积；去领取；募捐；赢得；（使）集中；接；领取（工资等）；推断；（使）马以受衔姿势跑；（非正式）和……互撞（collect 的过去式及过去分词）"},{"pos":"adj","trans":"（人）镇静的；收成全集的；合订的；（马奔跑时）步态稳健的"}],"pron":"/ kəˈlektɪd /","word":"collected"},{"defs":[{"pos":"abbr","trans":"西北（North-West）；西北的（NorthWestern）；净值（Net Worth）；航行警报（Navigation Warning）"}],"word":"nw"},{"defs":[{"pos":"n","trans":"乐队；法官"}],"pron":"/ bændz /","word":"bands"},{"defs":[{"pos":"n","trans":"靴子；猛踢；（汽车的）行李箱，后备箱；车轮固定夹；解雇；再者，除此之外（to boot）"},{"pos":"v","trans":"猛踢；锁住（非法停车的轮子）；启动（电脑）；在车轮上装制动装置；解雇；（使）穿靴"},{"pos":"","trans":"【名】 （Boot）（英、美、荷、加、德、意、俄）布特（人名）"}],"pron":"/ buːt /","word":"boot"},{"defs":[{"pos":"adj","trans":"适宜的，合适的"}],"pron":"/ ˈsuːtəbl /","word":"suitable"},{"defs":[{"pos":"abbr","trans":"固定的费用 (fixed fee)；灭火，消防 (fire fighting)；法拉第未来 (Faraday Future)"}],"pron":"/ ef ef /","word":"ff"},{"defs":[{"pos":"adv","trans":"绝对地，完全地；确实地，极其；（强调同意或允许）当然，对极了；专制地，独裁地"}],"pron":"/ ˈæbsəluːtli /","word":"absolutely"},{"defs":[{"pos":"n","trans":"数百万"}],"word":"millions"},{"defs":[{"pos":"n","trans":"午餐，午饭"},{"pos":"v","trans":"<正式>（尤指在餐馆）用午餐；请（人）吃午餐"}],"pron":"/ lʌntʃ /","word":"lunch"},{"defs":[{"pos":"n","trans":"人造阴茎"}],"pron":"/ ˈdɪldoʊ /","word":"dildo"},{"defs":[{"pos":"n","trans":"审计，查……的账目；审查，审核；审计报告"},{"pos":"v","trans":"审计，查账；<美>旁听"}],"pron":"/ ˈɔːdɪt /","word":"audit"},{"defs":[{"pos":"v","trans":"推，按；（尤指用力或努力）移动身体（或身体的一部分）；挤，推搡；敦促，强迫；努力争取，力劝；（军队）挺进，奋力前行；<非正式>推销，推广；贩卖（毒品）；坚持不懈地做；推进，推行；推动，促使（达到某程度或状态）；再三强调；超越（极限）；<非正式>接近（某年龄或数字）（be pushing）；赶走；推击（球）；使（栈）准备接收顶层数据；把（数据）移至栈的顶部；对（底片）作增感处理"},{"pos":"n","trans":"推 ；尝试，努力；鼓励，强迫；（军队的）挺进，猛攻 ；毅力，进取心；<非正式>棘手的事（a push）；按（机器或其他装置的部件）"}],"pron":"/ pʊʃ /","word":"push"},{"defs":[{"pos":"n","trans":"房间，室；会议厅，会所；议院；腔，膛；洞穴；<旧>卧室；法官办公室，律师事务所（chambers）"},{"pos":"v","trans":"把子弹送入弹膛；把……关在房间里"},{"pos":"adj","trans":"室内的；私人的，秘密的"},{"pos":"","trans":"【名】 （Chamber）（英）钱伯（人名）"}],"pron":"/ ˈtʃeɪmbər /","word":"chamber"},{"defs":[{"pos":"n","trans":"几内亚；基尼（英国旧时金币名）"}],"pron":"/ ˈɡɪni /","word":"guinea"},{"defs":[{"pos":"n","trans":"发现，调查结果；检验发现的情况（finding 复数）"}],"pron":"/ ˈfaɪndɪŋz /","word":"findings"},{"defs":[{"pos":"n","trans":"肌肉；体力，力气；权力，影响力；<非正式>身强力壮的男子（们）"},{"pos":"v","trans":"用力搬动；挤；<美，非正式> 以经济（或政治）压力迫使；加强"}],"pron":"/ ˈmʌs(ə)l /","word":"muscle"},{"defs":[{"pos":"v","trans":"以……为特色；由……主演；（在……中）起重要作用；显而易见；放映（电影），上演（戏剧）（feature 的现在分词）"}],"pron":"/ ˈfiːtʃərɪŋ /","word":"featuring"},{"defs":[{"pos":"abbr","trans":"国际标准化组织（International Standardization Organization）；国际科学组织（International Science Organization）"},{"pos":"n","trans":"（Iso）人名；（塞、芬、西）伊索"}],"pron":"/ ˈaɪsoʊˌˌaɪ es ˈoʊ /","word":"iso"},{"defs":[{"pos":"v","trans":"执行，贯彻；为……提供工具"},{"pos":"n","trans":"工具，器具；<苏格兰>履行；手段"}],"pron":"/ ˈɪmplɪmənt; ˈɪmpləˌment /","word":"implement"},{"defs":[{"pos":"n","trans":"微小静电干扰声"},{"pos":"v","trans":"点击（click 的 ing 形式）；发出滴答声"}],"pron":"/ ˈklɪkɪŋ /","word":"clicking"},{"defs":[{"pos":"adj","trans":"预先安排的，按时刻表的；（尤指航班）定期的；<英>（建筑，历史遗迹）列入文物保护单位的"},{"pos":"v","trans":"安排；将……列入计划表（或时间表等）；<英>把（建筑物）列为文物保护单位（schedule 的过去式和过去分词形式）"}],"pron":"/ ˈskedʒuːld /","word":"scheduled"},{"defs":[{"pos":"n","trans":"民意调查；投票；投票模块（poll 的复数形式）"},{"pos":"v","trans":"对……进行民意测验，使投票（poll 的单三形式）"}],"pron":"/ pəʊlz /","word":"polls"},{"defs":[{"pos":"adj","trans":"典型的，有代表性的；一贯的，平常的；不出所料，特有的；象征性的"}],"pron":"/ ˈtɪpɪkl /","word":"typical"},{"defs":[{"pos":"n","trans":"塔，塔楼；（发送信号等的）塔台；塔状堆积物；高柜，高架子；高层建筑，办公大楼；立式机箱；伦敦塔（the Tower）"},{"pos":"v","trans":"（比周围的人或物）高出许多，屹立；胜过，超过（其他人或机构）；（尤指猎鹰为捕抓猎物俯冲前）高飞，翱翔"},{"pos":"","trans":"【名】 （Tower）（英）托尔（人名）"}],"pron":"/ ˈtaʊər /","word":"tower"},{"defs":[{"pos":"pron","trans":"你（们）的东西；你的责任[义务]；你的家属；来信，尊函"},{"pos":"adj","trans":"你（们）的（东西）；信末署名前用语"}],"pron":"/ jɔːrz /","word":"yours"},{"defs":[{"pos":"n","trans":"金额，款项；算术，简单计算；总数，总和；全部，一切（尤指数量不大）；<英>计算失误；<英>计算费用"},{"pos":"v","trans":"概括，总结；求……的和，计算……的总数"},{"pos":"","trans":"【名】 （Sum）（英）萨姆，（柬）孙，（俄、德、捷）苏姆，（越）森（人名）"}],"pron":"/ sʌm /","word":"sum"},{"defs":[{"pos":"abbr","trans":"混杂的；各色各样混在一起；多才多艺的（miscellaneous）"}],"pron":"/ 'mɪsk /","word":"misc"},{"defs":[{"pos":"n","trans":"计算器"}],"pron":"/ ˈkælkjuleɪtər /","word":"calculator"}]