[{"defs":[{"pos":"n","trans":"（书、演讲、乐曲等的）段，章；（人生或体育赛事等中的）阶段；过道，走廊；（人群等中的）通道，通路；（人体的）管道；经过，穿过；（法案的）通过；通行权，通行许可；<旧>航程，航行；<正式>旅行，（尤指）转移；<旧>船费，机票；（时间的）推移，流逝；过渡，转变；（候鸟的）迁徙，迁移；（微生物的）传代，继代移种；巴沙基（盛装舞步和古典骑术的高抬腿舞步）"},{"pos":"v","trans":"使（微生物）继代移种，使传代；（使）通过通道"},{"pos":"","trans":"【名】 （Passage）（美）帕西奇（人名）"}],"pron":"/ ˈpæsɪdʒ /","word":"passage"},{"defs":[{"pos":"n","trans":"呼叫转移；已转运"},{"pos":"adj","trans":"转移的（transfer 过去式）；转让的；调动的"}],"word":"transferred"},{"defs":[{"pos":"n","trans":"树干；（人或动物的）躯干；象鼻；<美>（汽车后部的）行李箱，后备箱；旅行箱，衣箱；男式游泳裤（trunks）；大血管，神经干；电缆管道，通风管；拳击手短裤（trunks）"},{"pos":"adj","trans":"干线的"},{"pos":"","trans":"【名】 （Trunk）（德、匈、西）特伦克（人名）"}],"pron":"/ trʌŋk /","word":"trunk"},{"defs":[{"pos":"n","trans":"徒步旅行，远足"},{"pos":"v","trans":"去……远足；把（价格、税率等）大幅提高；拉起，提起（hike 的现在分词）"}],"pron":"/ ˈhaɪkɪŋ /","word":"hiking"},{"defs":[{"pos":"abbr","trans":"磅（源自拉丁语 libra，约等于454克）；（板球）触身得分（leg bye 或 leg byes）"},{"pos":"n","trans":"黎巴嫩（Lebanon）的互联网域名"}],"pron":"/ paʊnd /","word":"lb"},{"defs":[{"pos":"int","trans":"该死，见鬼（表示很生气或失望）；天啊（表示赞叹或惊奇）"},{"pos":"adj","trans":"该死的（表示对某人或某物生气）；（用于加强语气）十足的，完全的；"},{"pos":"adv","trans":"极其，非常；丝毫不"},{"pos":"v","trans":"严厉批评，谴责；（表愤怒或厌烦）该死，讨厌，混账；令（某人）下地狱；（强调对某事毫不在意）不管，无所谓；真没想到，真让我吃惊；决不，绝对不；贬斥，把……说得很糟糕；左右为难，做也不是，不做也不是；注定受难（或失败）；诅咒"},{"pos":"n","trans":"一点点，丝毫；（对……）在乎"}],"pron":"/ dæm /","word":"damn"},{"defs":[{"pos":"n","trans":"皮埃尔（男子名）"}],"pron":"/ pjeə /","word":"pierre"},{"defs":[{"pos":"n","trans":"耳机；头戴式受话器"}],"pron":"/ ˈhedset /","word":"headset"},{"defs":[{"pos":"n","trans":"照片，相片"},{"pos":"v","trans":"拍照，照相；在照片上显出某种样子"}],"pron":"/ ˈfoʊtəɡræf /","word":"photograph"},{"defs":[{"pos":"n","trans":"奥克兰（美国加州西部城市）"}],"pron":"/ ˈoʊklənd /","word":"oakland"},{"defs":[{"pos":"n","trans":"（Colombia）哥伦比亚"},{"pos":"n","trans":"（Colombia）（美）可罗姆碧艾（人名）"}],"pron":"/ kəˈlʌmbiə /","word":"colombia"},{"defs":[{"pos":"n","trans":"[物][军]波（wave 的复数形式）"},{"pos":"v","trans":"波动；起伏（wave 的第三人称单数形式）；挥动"}],"pron":"/ weɪvz /","word":"waves"},{"defs":[{"pos":"n","trans":"骆驼；驼绒织品；驼色，浅黄褐色；打捞浮筒"},{"pos":"adj","trans":"驼色的，暗棕色的"},{"pos":"","trans":"【名】 （Camel）（法）卡梅尔，（阿拉伯）卡迈勒（人名）"}],"pron":"/ ˈkæm(ə)l /","word":"camel"},{"defs":[{"pos":"n","trans":"经销商，批发商；（汽油发动机中的）配电器，配电盘"}],"pron":"/ dɪˈstrɪbjətər /","word":"distributor"},{"defs":[{"pos":"n","trans":"灯具（lamp 的复数）；眼睛；日月星辰"},{"pos":"v","trans":"看；照亮；发亮；放松（lamp 的第三人称单数）"},{"pos":"n","trans":"（Lamps）人名；（法）朗；（西）兰普斯"}],"pron":"/ læmps /","word":"lamps"},{"defs":[{"pos":"adj","trans":"根本的，潜在的；表面下的，下层的；优先的；（数量或水平）实际的"},{"pos":"v","trans":"位于…的下面；构成…的基础（underlie 的现在分词形式）"}],"pron":"/ ˌʌndərˈlaɪɪŋ /","word":"underlying"},{"defs":[{"pos":"n","trans":"（衣服上的）兜帽，风帽；头巾，面罩；（设备或机器的）防护罩，罩；汽车发动机罩；（炉灶上方的）排风罩，抽油烟罩；（汽车、婴儿车等）可折叠车篷；<美，非正式>恶棍，暴徒；<美，非正式>社区，街区；羽冠，垂兜，颈部皮褶；（野芝麻等植物的）盔状花冠；学位连领帽（表示学位种类）；（猎鹰）（鹰的）皮头罩"},{"pos":"v","trans":"加罩于，覆盖"},{"pos":"","trans":"【名】 （Hood）（英）胡德，（德、荷）霍德（人名）"}],"pron":"/ hʊd /","word":"hood"},{"defs":[{"pos":"n","trans":"摔跤运动"},{"pos":"v","trans":"（与某人）摔跤，扭打；使劲搬动，用力操作；努力解决，艰难对付（wrestle 的现在分词）"}],"pron":"/ ˈreslɪŋ /","word":"wrestling"},{"defs":[{"pos":"n","trans":"自杀；自杀者；自杀性的行为，自取灭亡的行为；<美>（篮球中的）自杀训练"},{"pos":"adj","trans":"自杀的，与自杀有关的"},{"pos":"v","trans":"自杀"}],"pron":"/ ˈsuːɪsaɪd /","word":"suicide"},{"defs":[{"pos":"adj","trans":"存档的；已归档的"},{"pos":"v","trans":"把……收集归档（archive 的过去分词）"}],"word":"archived"},{"defs":[{"pos":"n","trans":"著名图像处理软件（美国 Adobe 公司）"}],"pron":"/ ˈfoʊtoʊʃɑːp /","word":"photoshop"},{"defs":[{"pos":"abbr","trans":"喷气推进器（Jet Propulsion）；治安官（Justice of the Peace）"}],"pron":"/ ˌdʒeɪ ˈpiː /","word":"jp"},{"defs":[{"pos":"n","trans":"希腊文第二十二个字母"},{"pos":"n","trans":"（Chi）人名；（德）希；（柬）齐；（日）智（名）"}],"pron":"/ kaɪ /","word":"chi"},{"defs":[{"pos":"abbr","trans":"英国电信（British Telecom）"}],"pron":"/ ˌbiː ˈtiː /","word":"bt"},{"defs":[{"pos":"n","trans":"阿拉伯半岛（亚洲西南部，等于 Arabian Peninsula）"}],"pron":"/ əˈreɪbiə /","word":"arabia"},{"defs":[{"pos":"n","trans":"聚集，聚会；搜集，采集"},{"pos":"v","trans":"聚集，召集；收集，采集；认为，推断（gather 的现在分词形式）"}],"pron":"/ ˈɡæðərɪŋ /","word":"gathering"},{"defs":[{"pos":"n","trans":"估算，预测；投射，投影；（声音的）发送，放开；（思想感情的）体现，形象化；投射（不自觉地把自己的欲念等加诸他人）；凸出物，隆起物；（地球或天体在平面上的）投射；投影图；规划"}],"pron":"/ prəˈdʒekʃ(ə)n /","word":"projection"},{"defs":[{"pos":"n","trans":"（水果和蔬菜的）汁，水果（蔬菜）汁饮料；肉汁；<美，非正式>电，电能；胃液；精力，活力；<美，非正式>权势，影响力；<非正式>汽油；<美，非正式>酒"},{"pos":"v","trans":"榨（果汁或蔬菜汁）"}],"pron":"/ dʒuːs /","word":"juice"},{"defs":[{"pos":"v","trans":"追逐，追赶；匆忙赶往，急奔；追求，努力争取；求爱；驱逐，赶走；撤职；催促；镂刻，雕刻"},{"pos":"n","trans":"追赶，追逐；争取，努力获得；狩猎，猎捕；越野赛马，障碍赛马"},{"pos":"","trans":"【名】 （Chase）（英）蔡斯，（法）沙斯（人名）"}],"pron":"/ tʃeɪs /","word":"chase"},{"defs":[{"pos":"adj","trans":"有关数学的；具有数学头脑的；精确的，完整的；可能性极小的"}],"pron":"/ ˌmæθəˈmætɪkl /","word":"mathematical"},{"defs":[{"pos":"adj","trans":"合情合理的；合乎逻辑的；逻辑（上）的"}],"pron":"/ ˈlɑːdʒɪkl /","word":"logical"},{"defs":[{"pos":"n","trans":"酱，调味汁；<美，非正式>烈酒（the sauce）；<英，非正式> 无礼的话（或举动）"},{"pos":"v","trans":"加酱汁于，用酱汁调味；使增加趣味；<非正式>对……粗暴无礼"},{"pos":"","trans":"【名】 （Sauce）（西）绍塞，（法）索斯（人名）"}],"pron":"/ sɔːs /","word":"sauce"},{"defs":[{"pos":"n","trans":"名誉，名气"},{"pos":"v","trans":"使闻名，使有名望"}],"pron":"/ feɪm /","word":"fame"},{"defs":[{"pos":"n","trans":"选段，引文；提取物，汁"},{"pos":"v","trans":"提取，提炼；取出，拔出；摘录；索取，设法得到；开（方），求（根）"}],"pron":"/ ˈekstrækt /","word":"extract"},{"defs":[{"pos":"adj","trans":"专业的，专门的"},{"pos":"v","trans":"专门研究（或从事），专攻；专营；（生）使（器官）专化，使特化（specialize 的过去式和过去分词）"}],"pron":"/ ˈspeʃəlaɪzd /","word":"specialized"},{"defs":[{"pos":"adj","trans":"诊断的，判断的；（因症状特异而）能指示某种疾病性质的；（生物学上的某一物种、属类或现象所）特有的"},{"pos":"n","trans":"诊断程序, 诊断程式 （诊断计算机的错误）； 诊断提示（计算机错误的显示）；（特有的）症状（或特征）；诊断学，诊断法"}],"pron":"/ ˌdaɪəɡˈnɑːstɪk /","word":"diagnostic"},{"defs":[{"pos":"n","trans":"巴拿马（位于拉丁美洲）；巴拿马城"}],"pron":"/ ˈpænəmɑː /","word":"panama"},{"defs":[{"pos":"n","trans":"印第安纳波利斯（美国印第安纳州首府）"}],"pron":"/ ˌɪndiəˈnæpəlɪs /","word":"indianapolis"},{"defs":[{"pos":"abbr","trans":"视频，音频（audio frequency）；空军（Air Force）；法国航空公司（Air France）"},{"pos":"n","trans":"（Af）人名；（瑞典）阿夫"}],"word":"af"},{"defs":[{"pos":"adj","trans":"应付的；到期的；可付的；可获利的"},{"pos":"n","trans":"应付款"}],"pron":"/ ˈpeɪəb(ə)l /","word":"payable"},{"defs":[{"pos":"n","trans":"公司，企业（corporation 的复数）"}],"pron":"/ ˌkɔːrpəˈreɪʃ(ə)nz /","word":"corporations"},{"defs":[{"pos":"n","trans":"礼貌，彬彬有礼；礼貌的行为（言语）；<古>屈膝礼"},{"pos":"adj","trans":"免费提供的；礼节性的"}],"pron":"/ ˈkɜːrtəsi /","word":"courtesy"},{"defs":[{"pos":"n","trans":"批评，批判；意见；评论，评价；（对文学作品和历史文献的）考证"}],"pron":"/ ˈkrɪtɪsɪzəm /","word":"criticism"},{"defs":[{"pos":"n","trans":"汽车"}],"pron":"/ ˈɔːtəməbiːl /","word":"automobile"},{"defs":[{"pos":"adj","trans":"机密的，保密的；（言谈举止）神秘的，隐秘的；受信任的，委以机密的"}],"pron":"/ ˌkɑːnfɪˈdenʃ(ə)l /","word":"confidential"},{"defs":[{"pos":"abbr","trans":"请求注解（Request For Comments）；射频图（Radio Frequency Chart）；皇家陆军航空队（Royal Flying Corps）"}],"word":"rfc"},{"defs":[{"pos":"adj","trans":"依照法令的，法定的；成文法的，法令的；定期的，规则的"}],"pron":"/ ˈstætʃətɔːri /","word":"statutory"},{"defs":[{"pos":"n","trans":"住房，住宿；膳宿；居住设施（accommodation 的复数）"}],"pron":"/ əˌkɒməˈdeɪʃ(ə)nz /","word":"accommodations"},{"defs":[{"pos":"n","trans":"雅典（希腊首都）"}],"pron":"/ ˈæθənz /","word":"athens"},{"defs":[{"pos":"n","trans":"东北方，东北部"},{"pos":"adj","trans":"东北的；向东北的；（风等）来自东北的"},{"pos":"adv","trans":"在东北；向东北；（风等）来自东北"}],"pron":"/ ˌnɔːrθˈiːst /","word":"northeast"},{"defs":[{"pos":"v","trans":"（从计算机系统）下载（download 的过去式和过去分词）"}],"pron":"/ ˈdaʊnˌloʊdɪd /","word":"downloaded"},{"defs":[{"pos":"n","trans":"士师记（又译《民长记》，旧约全书之一卷）"}],"pron":"/ ˈdʒʌdʒɪz /","word":"judges"},{"defs":[{"pos":"abbr","trans":"海平面（sea level）；南纬度（south latitude）；透镜分光计（Lens Spectrometer）"}],"word":"sl"},{"defs":[{"pos":"abbr","trans":"搜索引擎优化（search engine optimization）；供股（seasoned equity offering）"}],"pron":"/ ˌes iː ˈoʊ /","word":"seo"},{"defs":[{"pos":"adj","trans":"退休的，退役的；（生活方式）隐居的，退隐的；（人）沉默寡言的，不好交际的；<古>（地方）僻静的，隐蔽的"},{"pos":"v","trans":"退休，退役；（因伤）退赛；撤退（retire 的过去式和过去分词形式）"}],"pron":"/ rɪˈtaɪərd /","word":"retired"},{"defs":[{"pos":"abbr","trans":"网络服务提供者（Internet Service Provider）；临时系统程序（Interim System Procedures）；内部存贮程序（Internally Stored Program）；双图像信号处理器（Image Sensor Processor）"}],"pron":"/ ˌaɪ es ˈpiː /","word":"isp"},{"defs":[{"pos":"n","trans":"评论（remark 的复数）；摘要；附注"}],"pron":"/ rɪˈmɑrk /","word":"remarks"},{"defs":[{"pos":"adj","trans":"检测到的"},{"pos":"v","trans":"（尤指用特殊方法）发现，识别；（通常指用特殊设备）探测，检测；查明，调查（罪犯，罪行）；察觉（细微或不易察觉的东西）（detect 的过去式和过去分词）"}],"pron":"/ dɪˈtektɪd /","word":"detected"},{"defs":[{"pos":"n","trans":"数十年（decade 的复数）"}],"pron":"/ ˈdekeɪdz /","word":"decades"},{"defs":[{"pos":"n","trans":"图画；印刷品（painting 的复数）；[涂料]涂漆"}],"pron":"/ ˈpeɪntɪŋz /","word":"paintings"},{"defs":[{"pos":"v","trans":"走路；散步（walk 的过去分词）"}],"pron":"/ wɔːkt /","word":"walked"},{"defs":[{"pos":"","trans":"出现"},{"pos":"","trans":"产生"}],"pron":"/ əˈraɪzɪŋ /","word":"arising"},{"defs":[{"pos":"n","trans":"（Nissan）尼桑（日产汽车名）"},{"pos":"n","trans":"（Nissan）（美、以、瑞典、加）内珊（人名）"}],"pron":"/ 'nɪsæn /","word":"nissan"},{"defs":[{"pos":"n","trans":"手镯，臂镯"}],"pron":"/ ˈbreɪslət /","word":"bracelet"},{"defs":[{"pos":"abbr","trans":"惯性导航系统（Inertial Navigation System）；国际新闻社（International News Service）；信息网络系统（Information Network System）"}],"pron":"/ ɪnz; ˌaɪ en ˈes /","word":"ins"},{"defs":[{"pos":"n","trans":"[禽]蛋（egg 的复数形式）；鸡蛋"}],"pron":"/ eɡz /","word":"eggs"},{"defs":[{"pos":"adj","trans":"青少年的，未成年的；少年犯的；幼稚的，孩子气的；（鸟或动物）幼年的"},{"pos":"n","trans":"青少年，未成年人；扮演青少年角色的演员；幼鸟，幼兽"}],"pron":"/ ˈdʒuːvənl /","word":"juvenile"},{"defs":[{"pos":"n","trans":"注射；大量资金的投入；（液体）注入，喷入；（宇宙飞船等的）射入轨道，入轨；内射，单射"}],"pron":"/ ɪnˈdʒekʃ(ə)n /","word":"injection"},{"defs":[{"pos":"n","trans":"约克郡（英格兰东北的一郡）"}],"pron":"/ ˈjɔrkʃər /","word":"yorkshire"},{"defs":[{"pos":"","trans":"[天][数][农] 总体"}],"word":"populations"},{"defs":[{"pos":"adj","trans":"保护的，防护的；呵护的，有保护欲的；有贸易保护倾向的，实行关税保护的"},{"pos":"n","trans":"<英>保护物，防护物；<旧>避孕套"}],"pron":"/ prəˈtektɪv /","word":"protective"},{"defs":[{"pos":"adj","trans":"害怕的；担心的；（害怕后果而）不愿意的，勉强的；遗憾的"}],"pron":"/ əˈfreɪd /","word":"afraid"},{"defs":[{"pos":"adj","trans":"声音的，听觉的；（乐器）原声的，不加电子设备传声的；（音乐）原声的，不经过电声设备放大的；（建筑材料）隔音的，修饰声音的；（装置，系统）利用声能运作的；（爆破性水雷或其他武器）能为声波引爆的"},{"pos":"n","trans":"（房间或建筑物的）音响效果，音质；声学（acoustics）；原声吉他（acoustic guitar）"}],"pron":"/ əˈkuːstɪk /","word":"acoustic"},{"defs":[{"pos":"n","trans":"<英>铁路，铁道；<英>铁路系统，铁路公司；<英>（其他交通工具使用的）轨道"}],"pron":"/ ˈreɪlweɪ /","word":"railway"},{"defs":[{"pos":"n","trans":"磁带盒，盒式磁带；胶片盒"}],"pron":"/ kəˈset /","word":"cassette"},{"defs":[{"pos":"adv","trans":"开始，最初"}],"pron":"/ ɪˈnɪʃəli /","word":"initially"},{"defs":[{"pos":"n","trans":"标志，迹象；方向灯，转向指示灯；指示器，显示器；指示剂；指示（物）种"}],"pron":"/ ˈɪndɪkeɪtər /","word":"indicator"},{"defs":[{"pos":"adj","trans":"尖的，尖角的，有尖头的；（言论或表情）尖锐的，直接的；明显的，突出的"}],"pron":"/ ˈpɔɪntɪd /","word":"pointed"},{"defs":[{"pos":"abbr","trans":"厚膛壁身管（Heavy Barrel）"},{"pos":"symb","trans":"(铅笔)硬黑"}],"word":"hb"},{"defs":[{"pos":"abbr","trans":"一种图像压缩格式（Joint Picture Group）"}],"word":"jpg"},{"defs":[{"pos":"vt","trans":"成为…的原因（cause的现在分词形式）"}],"pron":"/ ˈkɔːzɪŋ /","word":"causing"},{"defs":[{"pos":"n","trans":"错误，过失；（用词或数字上的）错误，口误，笔误；（令人后悔的）错误"},{"pos":"v","trans":"误解，误会；错误判断；把……误认为"}],"pron":"/ mɪˈsteɪk /","word":"mistake"},{"defs":[{"pos":"n","trans":"诺顿（男子名）；诺顿公司（美国一软件公司）"}],"pron":"/ ˈnɔːrtən /","word":"norton"},{"defs":[{"pos":"adj","trans":"（战斗或冲突）僵持不下的；上锁的"},{"pos":"v","trans":"锁上；紧闭；紧抱住（lock 的过去式和过去分词）"}],"pron":"/ lɒkt /","word":"locked"},{"defs":[{"pos":"v","trans":"剔除，根除；对……不予考虑，把……排除在外；（比赛中）淘汰；铲除，杀害；（生理）排除，排泄；消去"}],"pron":"/ ɪˈlɪmɪneɪt /","word":"eliminate"},{"defs":[{"pos":"abbr","trans":"技术委员会（Technical Committee）；油槽车（Tank Car）；温度系数（Temperature Coefficient）"}],"word":"tc"},{"defs":[{"pos":"n","trans":"融合，结合；核聚变；混合音乐；融合菜肴；熔化；融合物"}],"pron":"/ ˈfjuːʒn /","word":"fusion"},{"defs":[{"pos":"n","trans":"矿物质；矿物；<英>汽水，苏打水；无机物；矿泉水"},{"pos":"adj","trans":"（与）矿物（有关）的"}],"pron":"/ ˈmɪnərəl /","word":"mineral"},{"defs":[{"pos":"n","trans":"太阳镜；凸透镜（sunglass 的复数）"}],"pron":"/ ˈsʌnɡlæsɪz /","word":"sunglasses"},{"defs":[{"pos":"n","trans":"红宝石；深红色；（印刷）5点铅字"},{"pos":"adj","trans":"深红色的"},{"pos":"","trans":"【名】 （Ruby）（法）吕比，（英、西、德、匈、瑞典）鲁比（人名）"}],"pron":"/ ˈruːbi /","word":"ruby"},{"defs":[{"pos":"n","trans":"驾驶车（或船、飞机）；转向装置，操舵装置"},{"pos":"adj","trans":"（委员会或小组）筹划指导的"},{"pos":"v","trans":"驾驶（交通工具），掌方向盘；引导，指导（某人的行为）；引导，带领（某人去某地）（steer 的现在分词）"}],"pron":"/ ˈstɪrɪŋ /","word":"steering"},{"defs":[{"pos":"","trans":"玻璃粉"}],"pron":"/ biːdz /","word":"beads"},{"defs":[{"pos":"n","trans":"时运，命运；好运，机遇；财富，巨款；未来，前途"},{"pos":"v","trans":"给予财富；偶然发生"},{"pos":"","trans":"【名】 （Fortune） （英）福琼，（法）福蒂纳（人名）"}],"pron":"/ ˈfɔːrtʃən /","word":"fortune"},{"defs":[{"pos":"n","trans":"偏爱，偏好；更喜欢的人（或物）；优待，优先（权）；<法律>（尤指债务偿付）优先偿还权"}],"pron":"/ ˈprefrəns /","word":"preference"},{"defs":[{"pos":"n","trans":"帆布；画布，油画"},{"pos":"v","trans":"用帆布覆盖"}],"pron":"/ ˈkænvəs /","word":"canvas"},{"defs":[{"pos":"n","trans":"门槛，门口；阈，界，起始点；开端，起点，入门；机场跑道入口，跑道头"}],"pron":"/ ˈθreʃhoʊld /","word":"threshold"},{"defs":[{"pos":"n","trans":"教区，堂区；教区的居民，（尤指）教区教徒；<英>（农村的）行政堂区；<美>（路易斯安那州）堂区（相当于其他州的县）"}],"pron":"/ ˈpærɪʃ /","word":"parish"},{"defs":[{"pos":"v","trans":"声称；宣称；断言（claim 的过去式）"}],"pron":"/ kleɪmd /","word":"claimed"},{"defs":[{"pos":"n","trans":"屏幕（screen 的复数）；卡位"},{"pos":"v","trans":"遮蔽；拍电影（screen 的第三人称单数形式）"}],"pron":"/ skriːnz /","word":"screens"},{"defs":[{"pos":"n","trans":"公墓，墓地"}],"pron":"/ ˈseməteri /","word":"cemetery"}]