[{"defs":[{"pos":"n","trans":"马；<非正式>赛马；跳马，鞍马；锯木架；<非正式>马力；<美，非正式>主力队员；<非正式>海洛因；夹块，夹石；骑兵"},{"pos":"v","trans":"给（人或车辆）提供马；使骑马"}],"pron":"/ hɔːrs /","word":"horse"},{"defs":[{"pos":"v","trans":"投票选举，投票表决；投票评选；（通过投票）决定给予（资助），同意提供（款项）；表明，公认（某事好或坏）；投票同意；建议，主张"},{"pos":"n","trans":"选票，票；投票，表决；（选举中的）选票总数（the vote）；选举权，表决权；投票结果，表决结果；投票者，选民（the vote）；特定投票群体，特定选民"},{"pos":"","trans":"【名】 （Vote）（英、法）沃特（人名）"}],"pron":"/ voʊt /","word":"vote"},{"defs":[{"pos":"adv","trans":"向前；在船头，朝飞机头部；按顺序地；有进展地，前进地；向将来，往后；提前；（钟表）往前（拨）；从……起，自……以来"},{"pos":"adj","trans":"向前的，前进的；在前部的，位于前面的；（电子）正向的；未来的，将来的；期货的，预先的；早的，早熟的；鲁莽的，冒失的；热心的，动辄就……的"},{"pos":"n","trans":"（足球、篮球等运动的）前锋；（尤指金融市场）远期协议，远期交易"},{"pos":"v","trans":"转交，转寄；寄，发送；促进，推进"},{"pos":"","trans":"【名】 （Forward） （英、美、加、澳）福沃德（人名）"}],"pron":"/ ˈfɔːrwərd /","word":"forward"},{"defs":[{"pos":"","trans":"[植]花（flower 的复数）"},{"pos":"n","trans":"（Flowers）人名；（英）弗劳尔斯"}],"pron":"/ ˈflaʊərz /","word":"flowers"},{"defs":[{"pos":"n","trans":"明星类，明星（star 的复数形式）"},{"pos":"v","trans":"点缀；成辐射状开裂；使担任主角（star 的第三人称单数）"},{"pos":"abbr","trans":"specialized training and reassignment students经过专门训练后再分配的学生; stationary automotive road stimulator （Toyota）汽车公路固定刺激物（丰田汽车）"}],"pron":"/ stɑz /","word":"stars"},{"defs":[{"pos":"adj","trans":"显著的，相当数量的；重要的，意义重大的； 别有含义的，意味深长的"},{"pos":"n","trans":"<古>象征，有意义的事物"}],"pron":"/ sɪɡˈnɪfɪkənt /","word":"significant"},{"defs":[{"pos":"n","trans":"竞技场"},{"pos":"","trans":"竞技场围栏"}],"pron":"/ lɪsts /","word":"lists"},{"defs":[{"pos":"n","trans":"技术；科技（technology 的复数）"}],"pron":"/ tekˈnɑlədʒi /","word":"technologies"},{"defs":[{"pos":"n","trans":"所有人，物主"}],"pron":"/ ˈoʊnər /","word":"owner"},{"defs":[{"pos":"n","trans":"零售"},{"pos":"v","trans":"零售；以……价格销售；详说，述说（尤指别人的事情）"},{"pos":"adv","trans":"以零售方式"},{"pos":"adj","trans":"零售的"},{"pos":"","trans":"【名】 （Retail）（印）勒塔伊（人名）"}],"pron":"/ ˈriːteɪl /","word":"retail"},{"defs":[{"pos":"n","trans":"动物，动物世界；牲畜（animal 的复数）"}],"pron":"/ ˈænɪmlz /","word":"animals"},{"defs":[{"pos":"adj","trans":"有用的，有益的；<英，非正式>好的，熟练的"}],"pron":"/ ˈjuːsf(ə)l /","word":"useful"},{"defs":[{"pos":"adv","trans":"直接地，径直地；坦率地；恰好，正好；立即，很快地"},{"pos":"conj","trans":"一……就……"}],"pron":"/ dəˈrektli; daɪˈrektli /","word":"directly"},{"defs":[{"pos":"n","trans":"生产商，制造商"}],"pron":"/ ˌmænjuˈfæktʃərər /","word":"manufacturer"},{"defs":[{"pos":"n","trans":"方法（way 的复数）；滑路"},{"pos":"n","trans":"（Ways）人名；（吉布）瓦伊斯"}],"pron":"/ weɪz /","word":"ways"},{"defs":[{"pos":"abbr","trans":"美国东部标准时间（eastern standard time）；电休克疗法（electroshock therapy）；确立的（established）"},{"pos":"n","trans":"（Est）（美、俄、巴）埃斯特（人名）"}],"pron":"/ ˌiː es ˈtiː /","word":"est"},{"defs":[{"pos":"n","trans":"儿子；孩子（长者对男孩或年轻男子的称呼）；（某国或地区出生并能作其代表的）男性，子；圣子（耶稣基督）（the Son）；（动物的）雄性后代；男性后裔；（某个人、某种影响或某种环境）熏陶出的人；（司铎对男子或男孩的称呼）孩子（my son）"},{"pos":"","trans":"【名】 （Son）（土、老、柬）松，（法、罗）索恩，（日）存（人名）"}],"pron":"/ sʌn /","word":"son"},{"defs":[{"pos":"conj","trans":"假如，倘若（=providing that/provided）"},{"pos":"v","trans":"提供，给予；为（可能事件）做充分准备；抚养，赡养（provide 的现在分词）"}],"pron":"/ prəˈvaɪdɪŋ /","word":"providing"},{"defs":[{"pos":"n","trans":"规章，条例；（语言、科学等的）规则，法则；行事准则，指导方针；常规，惯常做法；统治，管辖；尺，直尺；铅线印出的线，破折号；<澳> 澳大利亚式橄榄球规则（两队各18人参赛）"},{"pos":"v","trans":"统治，管辖；支配，控制；占首要地位；（尤指对法律问题）判定，裁定；（用尺等）划（线）；<非正式> 好极了，非常棒；（行星）对（黄道十二宫图的宫，房子，生活等）有影响；（价格或贸易商品的价格）普遍处于某一水平（或坚挺趋势）"},{"pos":"","trans":"【名】 （Rule）（西）鲁莱（人名）"}],"pron":"/ ruːl /","word":"rule"},{"defs":[{"pos":"n","trans":"（非正式）雨衣"},{"pos":"n","trans":"（Mac）（美、丹等）马克（人名）"}],"pron":"/ mæk /","word":"mac"},{"defs":[{"pos":"n","trans":"房屋，住宅；住房供给，住房建设；（机器的）外壳，外罩；（木块上的）槽，榫眼；遮盖物，遮蔽物"},{"pos":"v","trans":"覆盖；给……房子住；把……储藏在房内（house 的现在分词形式）"}],"pron":"/ ˈhaʊzɪŋ /","word":"housing"},{"defs":[{"pos":"vt","trans":"取走，预备动作（take 第三人称单数）"}],"pron":"/ teɪks /","word":"takes"},{"defs":[{"pos":"num","trans":"罗马数字3"}],"pron":"/ θriː /","word":"iii"},{"defs":[{"pos":"abbr","trans":"格林威治标准时间（Greenwich Mean Time）；通用制图工具（Generic Mapping Tools）；地面移动目标（ground moving target）；玻纤毡增强热塑性片材（glass mat reinforced thermoplastics）"}],"pron":"/ ˌdʒiː em ˈtiː /","word":"gmt"},{"defs":[{"pos":"v","trans":"拿来，带来； 使……转入（新的话题）；移动；使处于某种状况；导致，引起；起诉；提供；强迫（自己）做；标价，售价为"},{"pos":"","trans":"【名】 （Bring）（英、瑞典）布林（人名）"}],"pron":"/ brɪŋ /","word":"bring"},{"defs":[{"pos":"n","trans":"[图情][计]目录；登记"},{"pos":"vt","trans":"登记；为……编目录"},{"pos":"vi","trans":"编目录；按确定价格收入目录（等于 catalogue）"}],"pron":"/ ˈkætəlɔːɡ /","word":"catalog"},{"defs":[{"pos":"n","trans":"[计][航][水运]搜索（search 的复数）；[计]检索"},{"pos":"v","trans":"搜寻；调查（search 的第三人称单数）"}],"pron":"/ ˈsɜːrtʃɪz /","word":"searches"},{"defs":[{"pos":"n","trans":"马克斯（男子名，同 Maximilian）"},{"pos":"abbr","trans":"（max）<非正式>最大的；最大限度的（同 maximum）"},{"pos":"n","trans":"（max）最大；最高，最重要的东西"},{"pos":"v","trans":"（max）达到最大限度"}],"pron":"/ mæks /","word":"max"},{"defs":[{"pos":"adj","trans":"令人厌烦的，难对付的"},{"pos":"v","trans":"试图，努力；试用，试做，试验；品尝（try 的现在分词形式）"}],"pron":"/ ˈtraɪɪŋ /","word":"trying"},{"defs":[{"pos":"n","trans":"母亲；大娘；女修道院院长"},{"pos":"vt","trans":"生下；养育；像母亲般关怀或照管"},{"pos":"adj","trans":"母亲的；出生地的"}],"pron":"/ ˈmʌðər /","word":"mother"},{"defs":[{"pos":"n","trans":"专家，权威人士；行政管理机构；权利，权限；权威，威信；许可，授权；当局，官方"}],"pron":"/ əˈθɔːrəti /","word":"authority"},{"defs":[{"pos":"adj","trans":"深思熟虑的"},{"pos":"v","trans":"考虑，斟酌；认为，视为；体贴，顾及（consider 的过去式和过去分词形式）"}],"pron":"/ kənˈsɪdərd /","word":"considered"},{"defs":[{"pos":"vt","trans":"告诉，说；辨别；吩咐；断定（tell的过去式和过去分词）"},{"pos":"vi","trans":"讲述；告发，泄密；识别（tell的过去式和过去分词）"}],"pron":"/ toʊld /","word":"told"},{"defs":[{"pos":"abbr","trans":"可扩展标示语言（Extensive Markup Language）"}],"pron":"/ ˌeks em ˈel /","word":"xml"},{"defs":[{"pos":"n","trans":"路上行驶的车辆，交通；（沿固定路线的）航行，行驶，飞行；运输量；非法交易；信息流量，通信（量）"},{"pos":"v","trans":"（非法）进行……交易，做……买卖；在……通行"}],"pron":"/ ˈtræfɪk /","word":"traffic"},{"defs":[{"pos":"n","trans":"计划，方案；（电视或广播的）节目；（戏剧或音乐会等演出的）说明书，节目单；（活动的）计划表，程序单；课程；（计算机等的）程序，程序设计"},{"pos":"v","trans":"（给计算机）编写程序，设计程序；调好，设置（机器使之按某种方式运作）；使……有倾向，使按某种方式行事；计划，安排"}],"pron":"/ ˈproʊɡræm /","word":"programme"},{"defs":[{"pos":"v","trans":"加入；参加（join 的过去式，过去分词）；[计]连接"}],"pron":"/ dʒɔɪnd /","word":"joined"},{"defs":[{"pos":"n","trans":"投入，输进；输入的信息；（为帮助某人做出决定而提供的）建议，意见；讯息输入端；（输入机器供其使用的）电力；输入框"},{"pos":"v","trans":"输入（信息）"}],"pron":"/ ˈɪnpʊt /","word":"input"},{"defs":[{"pos":"n","trans":"（尤指为获得某物制定长期的）策略，行动计划；战略，战略学"}],"pron":"/ ˈstrætədʒi /","word":"strategy"},{"defs":[{"pos":"n","trans":"脚（foot 的复数形式）；尺；韵脚"}],"pron":"/ fiːt /","word":"feet"},{"defs":[{"pos":"n","trans":"代理人，代理商；（艺术界的）经纪人；间谍，特工；原动力，动因；剂；（语法）施动者；（美国某些政府部门的）官员"},{"pos":"","trans":"【名】 （Agent）（罗）阿真特（人名）"}],"pron":"/ ˈeɪdʒənt /","word":"agent"},{"defs":[{"pos":"adj","trans":"（文件或票证）有效的；正当的，合理的；合法有效的；计算机系统接受的，被计算机系统认为有效的"}],"pron":"/ ˈvælɪd /","word":"valid"},{"defs":[{"pos":"n","trans":"垃圾桶；储物箱；瓶酒搁架；统计堆栈"},{"pos":"v","trans":"把……扔进垃圾箱；摒弃，拒绝；把……放（或贮藏）在箱（或仓）中；把（酒等）放进搁架；把（数据）归入统计堆"},{"pos":"","trans":"【名】 （Bin）（美、意）本（人名）"}],"pron":"/ bɪn /","word":"bin"},{"defs":[{"pos":"adj","trans":"近代的，现代的；当代风格的，现代派的；现代化的，新式的；摩登的，时髦的"},{"pos":"n","trans":"现代人；现代派艺术家；主张现代风格的人，宣扬现代价值观的人"}],"pron":"/ ˈmɑːdərn /","word":"modern"},{"defs":[{"pos":"adj","trans":"年龄大些的；（用在家庭内姓名相同的人名后表示）老，年长的；老年人的；（地位、水平或级别）较高的，高级的；（比赛）成人的，高水平的；<英>大于一定年龄（通常为11岁）的学童的；<美>（高中或大学）毕业年级的"},{"pos":"n","trans":"较年长的人；老年人，长者；地位（或级别）较高者，上司；<美>（中学或大学的）毕业班学生；资深成人运动员，高水平运动员"},{"pos":"","trans":"【名】 （Senior）（英）西尼尔（人名）"}],"pron":"/ ˈsiːniər /","word":"senior"},{"defs":[{"pos":"n","trans":"爱尔兰"}],"pron":"/ ˈaɪərlənd /","word":"ireland"},{"defs":[{"pos":"adj","trans":"性感的，引起性欲的；性兴奋的，性冲动的；<非正式>让人兴奋的，吸引人的"}],"pron":"/ ˈseksi /","word":"sexy"},{"defs":[{"pos":"n","trans":"教学工作，授课；教义，学说"},{"pos":"adj","trans":"教学的，与教学有关的"},{"pos":"v","trans":"教学；教训；教导（teach 的现在分词形式）"}],"pron":"/ ˈtiːtʃɪŋ /","word":"teaching"},{"defs":[{"pos":"n","trans":"门；门口，门道；建筑，门户 ；（尤与 open 或 unlock 连用）机会，可能性"},{"pos":"v","trans":"车门撞击（骑自行车经过的人）"},{"pos":"","trans":"【名】 （Door）（英）多尔（人名）"}],"pron":"/ dɔːr /","word":"door"},{"defs":[{"pos":"adj","trans":"壮丽的，堂皇的；宏伟的，宏大的；傲慢的，高高在上的；令人愉快的；<非正式>出色的，极好的；总括的；（常用于大型建筑物的名称前）大的；（对上层社会的人的称呼）大；（罪行）严重的；壮丽的，富丽堂皇的"},{"pos":"n","trans":"<非正式>一千美元，一千英镑；大钢琴，三角钢琴"},{"pos":"","trans":"【名】 （Grand）（英、瑞典）格兰德，（法）格朗（人名）"}],"pron":"/ ɡrænd /","word":"grand"},{"defs":[{"pos":"n","trans":"[试验]测试"},{"pos":"adj","trans":"试验的；棘手的"},{"pos":"v","trans":"测验；考查；受考验（test 的 ing 形式）"}],"pron":"/ ˈtestɪŋ /","word":"testing"},{"defs":[{"pos":"n","trans":"审判，审理；试验，试用；（对人的忍耐、自制力的）考验，磨练；烦人的事，惹麻烦的人；预赛，选拔赛；（检验车手技能的）摩托车障碍检验赛；（动物的）比赛，表演"},{"pos":"v","trans":"测试，试验；（马、狗等动物）参加比赛"},{"pos":"adj","trans":"试验性的"},{"pos":"","trans":"【名】 （Trial）（法）特里亚尔（人名）"}],"pron":"/ ˈtraɪəl /","word":"trial"},{"defs":[{"pos":"v","trans":"充电；使……承担责任，赋予……责任；控告，指控；（公开）指责，责备；进攻，冲锋；把……记在账上；要价，收费（金额）；<旧>给（枪炮）装弹；斟满（杯子）"},{"pos":"n","trans":"电量，电荷；炸药量；掌管，照管；费用，价钱；控告，指控；（书面或口头的）指责，批评；需要照管的人；命令，指示；（人或动物的）猛攻，冲锋；<美，非正式>快感，刺激；感召力，感染力；负载"},{"pos":"","trans":"【名】 （Charge）（英）查奇，（法）沙尔热（人名）"}],"pron":"/ tʃɑːrdʒ /","word":"charge"},{"defs":[{"pos":"n","trans":"[计量] 单位"}],"pron":"/ 'juːnɪts /","word":"units"},{"defs":[{"pos":"adv","trans":"代替，顶替，反而"}],"pron":"/ ɪnˈsted /","word":"instead"},{"defs":[{"pos":"adj","trans":"加拿大（人）的"},{"pos":"n","trans":"加拿大人"}],"pron":"/ kəˈneɪdiən /","word":"canadian"},{"defs":[{"pos":"adj","trans":"凉的，凉爽的；（衣服布料）使人凉爽的；冷静的，沉着的；时髦的，酷的；没问题，不介意；冷漠的，冷淡的；冷色调的；<非正式>（钱）大笔的，不折不扣的"},{"pos":"v","trans":"（使）冷却，（使）变凉；（感情）冷静下来，冷淡下来"},{"pos":"adv","trans":"<非正式>冷静地，镇定地"},{"pos":"n","trans":"凉快，凉爽；平静，镇静；时髦，酷"},{"pos":"","trans":"【名】 （Cool）（英）库尔，（法）科尔（人名）"}],"pron":"/ kuːl /","word":"cool"},{"defs":[{"pos":"adj","trans":"正常的，标准的；（身心）健康的，（人）普通的；（线或线性特征）正交的，垂直的；（盐溶液）与血液的盐浓度相同的；正（断层）的；平常的，通常的"},{"pos":"n","trans":"常态，通常标准；<非正式>正常人，循规蹈矩者；法线，正交"},{"pos":"","trans":"【名】 （Normal）（德）诺马尔（人名）"}],"pron":"/ ˈnɔːrm(ə)l /","word":"normal"},{"defs":[{"pos":"v","trans":"写（write 的过去式）"}],"pron":"/ roʊt /","word":"wrote"},{"defs":[{"pos":"n","trans":"企业，事业单位；事业心，进取心；事业；创业，企业经营"}],"pron":"/ ˈentərpraɪz /","word":"enterprise"},{"defs":[{"pos":"n","trans":"舰船（ship 的复数）"},{"pos":"v","trans":"船运（ship 的第三人称单数形式）"}],"pron":"/ ʃɪps /","word":"ships"},{"defs":[{"pos":"adj","trans":"全部的，整个的；完全的，绝对的；（公马）未经阉割的；（叶子）全缘的，边缘光滑的"},{"pos":"n","trans":"未经阉割的公马，种马"},{"pos":"","trans":"【名】 （Entire）（英）恩泰尔（人名）"}],"pron":"/ ɪnˈtaɪər /","word":"entire"},{"defs":[{"pos":"adj","trans":"教育的；有教育意义的"}],"pron":"/ ˌedʒuˈkeɪʃən(ə)l /","word":"educational"},{"defs":[{"pos":"abbr","trans":"总经理（Managing Director）；美国马里兰州（Maryland）；迷你光碟（mini disk）；医务部（Medical Department）; DOS 命令：建立一个新的子目录；肌肉萎缩症（muscular dystrophy）"}],"pron":"/ ˌem ˈdiː /","word":"md"},{"defs":[{"pos":"adj","trans":"主要的，最重要的；在（比赛或行列中）首位的，居前的"},{"pos":"n","trans":"行距；领导；（用于屋顶的）铅皮，铅板"},{"pos":"v","trans":"领导（lead 的现在分词形式）"}],"pron":"/ ˈliːdɪŋ; ˈledɪŋ /","word":"leading"},{"defs":[{"pos":"n","trans":"重金属音乐；金属色；筑路碎石；玻璃液；（铁路的）钢轨；金属，合金"},{"pos":"v","trans":"用金属做，用金属包；<英>用碎石筑路，用碎石修路"},{"pos":"adj","trans":"金属制的"},{"pos":"","trans":"【名】 （Metal）（捷、瑞典）梅塔尔（人名）"}],"pron":"/ ˈmetl /","word":"metal"},{"defs":[{"pos":"adj","trans":"乐观的，有信心的；积极的，建设性的；赞成的，支持的；确信的，肯定的；<非正式>完全的，绝对的；证据确凿的，明确的；阳性的；良好的，有助益的；正数的，大于零的；正电的，正极的；（摄影）正片的，正像的；赢利的；（语法）（形容词，副词）原级的；（主哲）实证的，实在的；（占星）（风宫，火宫）积极的"},{"pos":"n","trans":"优势，优点；正片；阳性结果；正数；（语法）原级形容词，原级副词"}],"pron":"/ ˈpɑːzətɪv /","word":"positive"},{"defs":[{"pos":"abbr","trans":"佛罗里达州（美国州名，Florida）；焦距（focal length）；外国语（foreign language）；呎朗伯（亮度单位）"}],"word":"fl"},{"defs":[{"pos":"n","trans":"健康；（生物体的）环境适度；适合，胜任"}],"pron":"/ ˈfɪtnəs /","word":"fitness"},{"defs":[{"pos":"adj","trans":"（Chinese）中国的；中国人的；汉语的"},{"pos":"n","trans":"（Chinese）中国人，华人；汉语；<非正式>中餐，中餐馆"},{"pos":"n","trans":"（Chinese）（美、印、澳、巴）奇内斯（人名）"}],"pron":"/ ˌtʃaɪˈniːz /","word":"chinese"},{"defs":[{"pos":"n","trans":"意见，看法；（群体的）观点，信仰；专家意见，专业意见；（对某人的）评价，印象；（法官或法院说明判决理由的）判决意见书"}],"pron":"/ əˈpɪnjən /","word":"opinion"},{"defs":[{"pos":"abbr","trans":"兆位，兆字节（mega byte）"}],"pron":"/ ˌem ˈbiː /","word":"mb"},{"defs":[{"pos":"n","trans":"亚洲"}],"pron":"/ ˈeɪʒə /","word":"asia"},{"defs":[{"pos":"n","trans":"足球运动；橄榄球运动；足球，橄榄球；屡起争议的课题，被踢来踢去的难题；（尤指别具一格的）足球风格，踢法"}],"pron":"/ ˈfʊtbɔːl /","word":"football"},{"defs":[{"pos":"adj","trans":"抽象的，纯概念的；（艺术）抽象派的；理论上的，不切实际的"},{"pos":"n","trans":"摘要，梗概；抽象画，抽象派艺术作品；抽象的概念"},{"pos":"v","trans":"抽象化，从理论上（或孤立地）考虑；提取，使分离；写……的摘要；偷走，窃取；退出"}],"pron":"/ ˈæbstrækt /","word":"abstract"},{"defs":[{"pos":"vt","trans":"使用，运用；利用；耗费（use 的第三人称单数）"},{"pos":"n","trans":"用途；耗费；（某单词的）用法（use 的复数）"},{"pos":"abbr","trans":"美国就业局（United States Employment Service）"}],"pron":"/ ˈjuːzɪz /","word":"uses"},{"defs":[{"pos":"n","trans":"产量，作品；产生，生产过程；输出功率；（计算机的）输出信息；输出端"},{"pos":"v","trans":"输出"}],"pron":"/ ˈaʊtpʊt /","word":"output"},{"defs":[{"pos":"n","trans":"[会计]资金，现金（fund 的复数）；基金"},{"pos":"v","trans":"资助（fund 的三单形式）；提供资金"}],"pron":"/ fʌndz /","word":"funds"},{"defs":[{"pos":"n","trans":"（用于男子的姓或姓名前）先生；（称呼要员）先生"}],"pron":"/ ˈmɪstər /","word":"mr"},{"defs":[{"pos":"adj","trans":"较大的（great 的比较级）"}],"pron":"/ ˈɡreɪtər /","word":"greater"},{"defs":[{"pos":"adj","trans":"可能发生的；似乎合适的，仿佛恰当的；似乎真实的，可信的；看上去精力充沛（或有能力）的"},{"pos":"adv","trans":"大概，很可能"}],"pron":"/ ˈlaɪkli /","word":"likely"},{"defs":[{"pos":"v","trans":"（使）成长，发育，发展；逐渐形成，逐渐养成；开发，研制；出现，产生；修建，开发土地；提高，加强；患病；阐释，展开；冲洗，使底片显影；（修改旋律、和声或节奏以）展开（音乐主题）；（棋）出子"}],"pron":"/ dɪˈveləp /","word":"develop"},{"defs":[{"pos":"n","trans":"员工；雇员；从业人员（employee 的复数）"}],"pron":"/ ɪmˈplɔɪiːz /","word":"employees"},{"defs":[{"pos":"n","trans":"艺术家，设计师（artist 的复数）"}],"word":"artists"},{"defs":[{"pos":"n","trans":"可供选择的事物，替代物"},{"pos":"adj","trans":"可替代的，备选的；非传统的，另类的；（两者）互不相容的，非此即彼的"}],"pron":"/ ɔːlˈtɜːrnətɪv /","word":"alternative"},{"defs":[{"pos":"n","trans":"加工；处理；运算"},{"pos":"v","trans":"加工；处理；审阅，审核（文件或请求等）；对……起诉；列队进行；冲印（照片）（process 的现在分词）"}],"pron":"/ ˈprɑːsesɪŋ /","word":"processing"},{"defs":[{"pos":"n","trans":"责任，负责；（对不良事件所负的）责任；（道义上或法律规定的）责任（responsibility to/towards）；职责，任务；重任，职权"}],"pron":"/ rɪˌspɑːnsəˈbɪləti /","word":"responsibility"},{"defs":[{"pos":"n","trans":"决议，正式决定；（冲突、问题等的）解决，解决办法；决心，决定；坚决，果断；（电视、照相机、显微镜等的）清晰度，分辨率；（故事中主要矛盾的）冲突解开；（乐）解决（指和声中不协和音向协和音的进行）；（医）（炎症或其他症状的）消散，消退；（化）分解；（物理）（力或其他矢量的）分解"}],"pron":"/ ˌrezəˈluːʃn /","word":"resolution"},{"defs":[{"pos":"n","trans":"（非正式）咖啡"},{"pos":"n","trans":"（Java） Java 语言（一种计算机编程语言）；爪哇岛"},{"pos":"n","trans":"（Java）（印、美）杰娃（人名）"}],"pron":"/ ˈdʒɑːvə /","word":"java"},{"defs":[{"pos":"n","trans":"客人；特邀嘉宾，客串演员；顾客，房客；寄居昆虫"},{"pos":"v","trans":"做特邀嘉宾，客串"},{"pos":"","trans":"【名】 （Guest）（英）格斯特（人名）"}],"pron":"/ ɡest /","word":"guest"},{"defs":[{"pos":"v","trans":"（涉及推断）似乎，看来；（用于表示谨慎、礼貌或委婉）好像，可能(seem 的第三人称单数)"},{"pos":"","trans":"【名】 （Seem）（英）西姆（人名）"}],"pron":"/ siːm /","word":"seems"},{"defs":[{"pos":"n","trans":"出版，发行；出版物，发行物；（信息的） 刊登，公布"}],"pron":"/ ˌpʌblɪˈkeɪʃn /","word":"publication"},{"defs":[{"pos":"v","trans":"经过，越过；前行，穿过；使穿过；传递，传送；传达（信息）；传（球）；（所有权）转移，转让；转变，转化；交流，交换；（数量上）超过，突破；（时间）流逝；度过，消磨；通过（考试、课程等）；使及格，使通过；（尤指以投票方式）通过（法律或提案）；（立法等）获得通过，被批准；略过（问题）；过得去，还行；排泄；使（货币等）流通；结束，停止；去世；拒绝邀请（提议）；传染；用假币支付；发生；提出（批评或意见）；（纸牌等游戏中）不叫，过；传播，散布；（依法）给予某人；宣布，声明"},{"pos":"n","trans":"出入证，通行证；及格，合格；传球；山道，山口；阶段，步骤；（计算机）一次浏览，一次扫描；飞越；变戏法；（击剑中的）戳刺；（不好的）境遇，处境；（桥牌）不叫"},{"pos":"","trans":"【名】 （Pass）（德、英）帕斯（人名）"}],"pron":"/ pæs /","word":"pass"},{"defs":[{"pos":"n","trans":"关系；交往；事务"}],"pron":"/ rɪˈleɪʃnz /","word":"relations"},{"defs":[{"pos":"n","trans":"信任，信赖；（金钱或财产的）信托，托管；受托基金机构，受托团体；代管的财物，托管的财物；公立医院（由政府资助、独立经营）；<美>托拉斯托拉斯，垄断企业；受托，受委任；<文>被托付的人，被赋予的职责；<文>希望，期待"},{"pos":"v","trans":"信任，相信；对……有把握，信得过；坚信，信仰；希望，盼望；托交，托付；<古>赊账"},{"pos":"","trans":"【名】 （Trust）（英）特拉斯特（人名）"}],"pron":"/ trʌst /","word":"trust"},{"defs":[{"pos":"n","trans":"（厢式）小型货车；<美>面包车；<英>（铁路上运送包裹、邮件等的）车厢；<英>拖车；先锋"},{"pos":"v","trans":"用车搬运"},{"pos":"","trans":"【名】 （Van）（老、泰、柬、缅）万（人名）"}],"pron":"/ væn /","word":"van"},{"defs":[{"pos":"v","trans":"包含，容纳；控制，克制；由……组成；可整除；防止……蔓延（contain 的第三人称单数）"}],"pron":"/ kənˈteɪnz /","word":"contains"},{"defs":[{"pos":"n","trans":"（某项活动的）一段时间，一场；（议会等的）会议，（法庭的）开庭；学年，上课时间；（酒吧中）演奏会（尤指演奏爱尔兰音乐）；（尤指录音师的）灌录音乐时间；<非正式>酗酒期；基督教长老会的管理机构"},{"pos":"adj","trans":"（音乐家）伴奏的"}],"pron":"/ ˈseʃn /","word":"session"},{"defs":[{"pos":"pref","trans":"多"}],"pron":"/ ˈmʌlti /","word":"multi"},{"defs":[{"pos":"n","trans":"摄影，摄影术；摄影影像，摄影图片"}],"pron":"/ fəˈtɑːɡrəfi /","word":"photography"}]