[{"defs":[{"pos":"n","trans":"已坏"}],"word":"ooo"},{"defs":[{"pos":"abbr","trans":"赫兹（hertz）"}],"pron":"/ eɪtʃ ˈziː; hɜːrts /","word":"hz"},{"defs":[{"pos":"v","trans":"使改观，使变形，使转化；变换（电流）的电压；（数）变换（数学实体）"},{"pos":"n","trans":"（数，语言学）变换式，转换句；（数，语言学）转换规则"}],"pron":"/ trænsˈfɔːrm /","word":"transform"},{"defs":[{"pos":"n","trans":"[电子] 定时器；计时器；计时员，记时员；跑表；延时调节器"}],"pron":"/ ˈtaɪmər /","word":"timer"},{"defs":[{"pos":"n","trans":"[药]药片，匾（tablet 的复数形式）；便笺"},{"pos":"v","trans":"用碑牌纪念；将……制成小片（tablet 的第三人称单数）"}],"pron":"/ 'tæblɪts /","word":"tablets"},{"defs":[{"pos":"n","trans":"调音；起音，定音；音调；（电子或收音机）调谐；协调一致"}],"pron":"/ ˈtjʊnɪŋ /","word":"tuning"},{"defs":[{"pos":"v","trans":"得到；达到（get 的过去分词）"}],"pron":"/ ˈɡɑːtn /","word":"gotten"},{"defs":[{"pos":"","trans":"教育工作者"},{"pos":"","trans":"教育家（educator 的复数）"}],"pron":"/ ˈedʒukeɪtəz /","word":"educators"},{"defs":[{"pos":"n","trans":"泰勒（男子名）；秘密会所看守人（共济会的）"}],"word":"tyler"},{"defs":[{"pos":"n","trans":"期货；未来，前途（future 的复数形式）"}],"pron":"/ ˈfjʊtʃərz /","word":"futures"},{"defs":[{"pos":"n","trans":"蔬菜；植物人；呆板懒散的人；植物"},{"pos":"adj","trans":"植物的"}],"pron":"/ ˈvedʒtəbl /","word":"vegetable"},{"defs":[{"pos":"n","trans":"诗，韵文；诗节，（歌曲的）节；（《圣经》或其他经文的）节，句；（赞美诗的）独唱部，小组唱部"},{"pos":"v","trans":"<古>作诗"},{"pos":"","trans":"【名】 （Verse）（德）费尔泽（人名）"}],"pron":"/ vɜːrs /","word":"verse"},{"defs":[{"pos":"adj","trans":"高的；富含……的；重要的；先进的，高级的；崇高的；高音的，声音尖锐的；兴高采烈的；喝醉了的，（吸毒后）极度兴奋的；十分赞同的，非常尊敬的；中间的，全盛的；开始变质的，开始发馊的；（宗教或政治观点）极端的，偏激的；（元音）舌位高的"},{"pos":"n","trans":"最高水平，最大数量；兴奋，高兴；高气压区；（毒品引致的）快感；高中，中学；强档；高音，高音符"},{"pos":"adv","trans":"（成本、价值、音量）高，（数量）大；在高处，向高处"},{"pos":"","trans":"【名】 （High）（英）海伊（人名）"}],"pron":"/ haɪ /","word":"highs"},{"defs":[{"pos":"n","trans":"人文学科（humanity 的复数）"}],"pron":"/ hjʊˈmænətɪz /","word":"humanities"},{"defs":[{"pos":"adv","trans":"独立地；自立地"}],"pron":"/ ˌɪndɪˈpendəntli /","word":"independently"},{"defs":[{"pos":"v","trans":"想要；需要……在场；对……有性欲；缺少；想请教；（警方）缉拿；（非正式）需要；（非正式）应该；缺少（一定的量或某个东西）；要求（某人）到来（want 的现在分词）"},{"pos":"adj","trans":"缺乏的；欠缺的；不存在的，没有的；（非正式）弱智的"},{"pos":"prep","trans":"没有；除去"}],"pron":"/ ˈwɑːntɪŋ /","word":"wanting"},{"defs":[{"pos":"n","trans":"监护，监护权；监禁，拘留；保管，保护"}],"pron":"/ ˈkʌstədi /","word":"custody"},{"defs":[{"pos":"v","trans":"（用指甲）挠，轻抓；（用指甲或利器）抓破，划破；划出，刮出（痕迹）；（用爪子）抓，刨；（鸟、哺乳动物，尤指鸡）用嘴（或爪子）扒地找食物；寻觅（难找的人或物）（scratch for）；艰难生活（scratch along）；勾掉，划去（写下的字）；<非正式> 仓促写下；（用尖利物）刮擦出声音；<非正式> 取消，撤销（想法或计划）；<非正式>（使）退出比赛；（用刮擦技法）播放唱片"},{"pos":"n","trans":"（某人皮肤上的）划痕，划伤；刮痕，划痕；抓，挠；刮擦声 ；唱片的嚓嚓声（指唱片纹道与唱针的摩擦噪声）；刮擦（多用于快板乐中，用手制止唱片转动，使其来回移动发出有节奏的嚓嚓声的技巧）；（高尔夫）零让步（表明选手不弱，能在场上达到规定击球的次数）；<非正式> 钱"},{"pos":"adj","trans":"（球队或一群人等）仓促拼凑的，匆匆组成的；（高尔夫球员）无让杆的，无让步优待的；碰巧的；打草稿用的"}],"pron":"/ skrætʃ /","word":"scratch"},{"defs":[{"pos":"n","trans":"汽艇（launch 的复数）"},{"pos":"v","trans":"[航]发射；下水；投入（launch 的单三形式）"}],"pron":"/ ˈlɔːntʃɪz /","word":"launches"},{"defs":[{"pos":"n","trans":"排成直线，摆放恰当；结盟；协调，一致；（铁路或道路的）路线；石排"}],"pron":"/ əˈlaɪnmənt /","word":"alignment"},{"defs":[{"pos":"","trans":"（对……）进行手淫（masturbate 的现在分词）"}],"pron":"/ ˈmæstəbeɪtɪŋ /","word":"masturbating"},{"defs":[{"pos":"n","trans":"亨德森（姓氏）"}],"pron":"/ ˈhendərsən /","word":"henderson"},{"defs":[{"pos":"","trans":"布鲁克林（Brooklyn）"}],"word":"bk"},{"defs":[{"pos":"n","trans":"大英百科全书"}],"pron":"/ brɪˈtænɪkə /","word":"britannica"},{"defs":[{"pos":"abbr","trans":"通信（communication）；商业，贸易（commerce）；委员会（committee）"},{"pos":"n","trans":"（Comm）（美、印、加）科姆（人名）"}],"pron":"/ kɑːm /","word":"comm"},{"defs":[{"pos":"n","trans":"埃伦（女子名）"}],"pron":"/ ˈelən /","word":"ellen"},{"defs":[{"pos":"n","trans":"竞争对手；[劳经]竞争者（competitor 的复数）"}],"pron":"/ kəmˈpetətər /","word":"competitors"},{"defs":[{"pos":"abbr","trans":"英国国民健康保险制度（National Health Service）"}],"pron":"/ ˌen eɪtʃ ˈes /","word":"nhs"},{"defs":[{"pos":"n","trans":"火箭；火箭发动机（=rocket engine/rocket motor）；火箭武器，火箭弹；火箭式焰火，流星焰火（=skyrocket）；<英>芝麻菜，大蒜芥；<英，非正式>严厉的斥责；（像火箭般）快速行动者，飞快行进的物体"},{"pos":"v","trans":"快速增长，猛增；迅速移动，飞速行进；用火箭武器攻击；（使）迅速成功，迅速提高地位；用火箭运载"}],"pron":"/ ˈrɑːkɪt /","word":"rocket"},{"defs":[{"pos":"adv","trans":"赞成；是，对；总是，仍旧"},{"pos":"n","trans":"赞成票；投赞成票者；赞成"},{"pos":"int","trans":"哎，表示痛苦或吃惊"},{"pos":"n","trans":"（Aye）（美、法、新）阿耶（人名）"}],"pron":"/ aɪ /","word":"aye"},{"defs":[{"pos":"n","trans":"子弹，弹丸；（标示用的）黑圆点；<美>（运动中）高速球"},{"pos":"","trans":"【名】 （Bullet）（法）比莱（人名）"}],"pron":"/ ˈbʊlɪt /","word":"bullet"},{"defs":[{"pos":"n","trans":"[建]塔；塔器；空中跳台（tower 的复数）"},{"pos":"n","trans":"（Towers）人名；（英）托尔斯"}],"pron":"/ ˈtaʊərz /","word":"towers"},{"defs":[{"pos":"n","trans":"货架；[交]行李架；拷问台（rack 的复数形式）"},{"pos":"v","trans":"折磨；使……痛苦；加以拷问（rack 的三单形式）"}],"pron":"/ ræks /","word":"racks"},{"defs":[{"pos":"n","trans":"网眼织物，蕾丝；鞋带，系带；少量烈酒"},{"pos":"v","trans":"用系带束紧，用鞋带系（鞋）；把（少量酒、药品或毒药等烈性物质）掺入；使编织（或交织、缠绕）在一起；加入……使有味（或有趣）"},{"pos":"","trans":"【名】 （Lace）（意）拉切（人名）"}],"pron":"/ leɪs /","word":"lace"},{"defs":[{"pos":"adj","trans":"恶毒的，凶相的；令人不快的，令人厌恶的；（伤口、疾病等）严重的，恶性的；污秽的，下流的；（外表）丑陋的，（气味等）难闻的；造成很大伤害的；令人担忧的，难对付的；有威胁性的，吓人的"},{"pos":"n","trans":"<非正式>令人不快的人（或事），危害别人的人（或事）；<非正式>恐怖录像（或影片）"},{"pos":"","trans":"【名】 （Nasty）（美、俄、印）耐史迪（人名）"}],"pron":"/ ˈnæsti /","word":"nasty"},{"defs":[{"pos":"n","trans":"能见度，能见距离；可见性，明显性；关注度，知名度"}],"pron":"/ ˌvɪzəˈbɪləti /","word":"visibility"},{"defs":[{"pos":"n","trans":"纬度；纬度地区；选择的自由，回旋余地；（感光乳剂，相纸）曝光宽容度"}],"pron":"/ ˈlætɪtuːd /","word":"latitude"},{"defs":[{"pos":"n","trans":"知觉，清醒；思想，意识；（群体的）观念体系；感知，察觉"}],"pron":"/ ˈkɑːnʃəsnəs /","word":"consciousness"},{"defs":[{"pos":"abbr","trans":"专用测试设备（Special Test Equipment）；（英）电信工程师学会（Society of Telecommunications Engineers）；适合配性试验的鉴定（Suitability Test Evaluation）"}],"word":"ste"},{"defs":[{"pos":"n","trans":"肿瘤；肿块；赘生物"}],"pron":"/ ˈtuːmər /","word":"tumor"},{"defs":[{"pos":"adj","trans":"丑陋的，难看的；（通常因涉及暴力、挑衅行为而）令人厌恶的，邪恶的，恶性的；无礼的；道德败坏的；可怕的，恐怖的；难听的，不悦耳的"}],"pron":"/ ˈʌɡli /","word":"ugly"},{"defs":[{"pos":"n","trans":"[金融]存款；[地质]沉积物（deposit 的复数）；订金"},{"pos":"v","trans":"[地质]沉积（deposit 的单三形式）；存储；付保证金"}],"pron":"/ dɪˈpɑzɪt /","word":"deposits"},{"defs":[{"pos":"n","trans":"（Beverly）（美）贝弗莉（人名）"}],"pron":"/ ˈbevərli /","word":"beverly"},{"defs":[{"pos":"n","trans":"情妇；<英>女教师；（奴仆的）女主人；（宠物的）女主人；绝对控制……的女人，主宰……的女人；（精通某项活动的）女能手，女行家；女士（用作女子姓氏或姓名前的称呼）；<英>女院长 (Mistress)"}],"pron":"/ ˈmɪstrəs /","word":"mistress"},{"defs":[{"pos":"v","trans":"遭遇；偶遇，邂逅"},{"pos":"n","trans":"偶遇，邂逅；经历，体验；冲突；比赛，交锋"}],"pron":"/ ɪnˈkaʊntər /","word":"encounter"},{"defs":[{"pos":"n","trans":"[法]受托人，受托者（trustee 的复数形式）"}],"pron":"/ trʌs'tiz /","word":"trustees"},{"defs":[{"pos":"n","trans":"瓦特（功率单位）"}],"pron":"/ wɑːts /","word":"watts"},{"defs":[{"pos":"n","trans":"邓肯（姓氏）"}],"pron":"/ ˈdʌŋkən /","word":"duncan"},{"defs":[{"pos":"n","trans":"再版本；[图情]重印本（reprint 的复数）"},{"pos":"v","trans":"[印刷]重印；再版；加洗（reprint 的三单形式）"}],"pron":"/ ˌriːˈprɪnts /","word":"reprints"},{"defs":[{"pos":"n","trans":"雄赤鹿（复数 harts）"},{"pos":"n","trans":"（Hart）人名；（匈）豪尔特；（西、法）阿特；（英、罗、捷、芬、德）哈特"}],"pron":"/ hɑːrt /","word":"hart"},{"defs":[{"pos":"n","trans":"伯纳德（男子名）"}],"pron":"/ bərˈnɑːrd /","word":"bernard"},{"defs":[{"pos":"n","trans":"决议（resolution 的复数）；解决；决心；[物]分辨率"}],"pron":"/ ˌrezəˈlʊʃən /","word":"resolutions"},{"defs":[{"pos":"suff","trans":"……的结果或手段（后缀，与动词结合构成名词）"}],"pron":"/ mənt /","word":"ment"},{"defs":[{"pos":"n","trans":"（计算机）访问"},{"pos":"v","trans":"（计算机）访问；接近；到达（access 的现在分词）"}],"pron":"/ ˈæksesɪŋ /","word":"accessing"},{"defs":[{"pos":"n","trans":"四十"},{"pos":"adj","trans":"四十的；四十个的"}],"pron":"/ ˈfɔːrti /","word":"forty"},{"defs":[{"pos":"n","trans":"[材]管子，导管；管状虫；伦敦地铁（tube 的复数）"}],"pron":"/ tjʊb /","word":"tubes"},{"defs":[{"pos":"adj","trans":"企图的；未遂的"},{"pos":"v","trans":"企图（attempt 的过去式）"}],"pron":"/ əˈtemptɪd /","word":"attempted"},{"defs":[{"pos":"n","trans":"山坳；出口；峡路"}],"pron":"/ kɑːl /","word":"col"},{"defs":[{"pos":"","trans":"中部地区"}],"pron":"/ ˈmɪdləndz /","word":"midlands"},{"defs":[{"pos":"n","trans":"牧师，神职人员；木渔槌（垂钓时用以打死已上钩的鱼）"},{"pos":"v","trans":"<正式>任命……为司铎（或祭司）"},{"pos":"","trans":"【名】 （Priest）（英、德）普里斯特（人名）"}],"pron":"/ priːst /","word":"priest"},{"defs":[{"pos":"n","trans":"弗洛伊德（男子名）"}],"pron":"/ flɔɪd /","word":"floyd"},{"defs":[{"pos":"n","trans":"罗纳德（男子名）"}],"pron":"/ ˈrɑːnld /","word":"ronald"},{"defs":[{"pos":"n","trans":"分析师；分析家；[分化]分析员（analyst 的复数）"}],"pron":"/ 'ænəlɪsts /","word":"analysts"},{"defs":[{"pos":"n","trans":"<英>（人、汽车等的）队，行列；<英>（为得到某机会而等待的）长列，长队；（计算机）队列；呼叫队列；<古>辫子"},{"pos":"v","trans":"<英>排队（等候）；竞相，抢着（做某事）；（计算机）排成队列，排队"}],"pron":"/ kjuː /","word":"queue"},{"defs":[{"pos":"abbr","trans":"试验驱逐舰（Destroyer Experimental）；远程接收或传输（Distance Reception or Transmission）；远程无线电通信（Distant Radio Communication）；双工接收器（Duplex Repeater）；高级的（deluxe）"}],"word":"dx"},{"defs":[{"pos":"abbr","trans":"袋（sack）；链球菌激酶（streptokinase）"}],"word":"sk"},{"defs":[{"pos":"n","trans":"恍惚；出神；着迷，入迷"},{"pos":"vt","trans":"使恍惚；使发呆"}],"pron":"/ træns /","word":"trance"},{"defs":[{"pos":"n","trans":"（事情发生的）地点，现场"}],"pron":"/ loʊˈkæl /","word":"locale"},{"defs":[{"pos":"n","trans":"尼古拉斯（男子名）"}],"pron":"/ ˈnɪkələs /","word":"nicholas"},{"defs":[{"pos":"abbr","trans":"生物学（biological）"}],"word":"biol"},{"defs":[{"pos":"n","trans":"禹（传说的中国古代圣君）"}],"word":"yu"},{"defs":[{"pos":"n","trans":"束，捆，包；非常；一套，一系列；大量；婴儿；一大笔钱；软件包"},{"pos":"v","trans":"匆匆打发，乱塞；匆忙赶往；捆绑销售；与某人和衣同睡"}],"pron":"/ ˈbʌnd(ə)l /","word":"bundle"},{"defs":[{"pos":"n","trans":"锤子，榔头；（拍卖用的）木槌；链球；击铁；音槌；锣锤"},{"pos":"v","trans":"（用锤子）敲击；用力敲打，猛踢；强行灌输，反复强调；（在体育比赛中）使惨败，大败；使（企业）受到打击；严厉批评，指责；（心脏）剧烈跳动；压低（某股票）的价格"},{"pos":"","trans":"【名】 （Hammer）（美、德、挪、奥、俄、丹、加、巴）阿梅（人名）"}],"pron":"/ ˈhæmər /","word":"hammer"},{"defs":[{"pos":"n","trans":"侵略，入侵；涌入，大批进入；侵犯，干预；侵袭，扩散"}],"pron":"/ ɪnˈveɪʒn /","word":"invasion"},{"defs":[{"pos":"n","trans":"[法]证人；目击者；[法]证据（witness 的复数）"},{"pos":"v","trans":"作证；目睹（witness 的三单形式）"}],"pron":"/ ˈwɪtnəsiz /","word":"witnesses"},{"defs":[{"pos":"n","trans":"跑步者，赛跑的人；赛跑的动物（如马）；<加拿大>跑鞋，运动鞋；性能良好的车（或机器）；（公司或组织中的）跑腿的人，外勤人员；（部队的）传令兵，通讯员；<英，非正式>个体古董商；<英，非正式>（工作或职位的）争夺者，竞争者；<英，非正式>可能被接受的想法，切实可行的建议；（棒球中的）跑垒者；（在三柱门之间为受伤的击球手跑动的）跑动板球员；毒品（或武器）走私者； （金属、塑料或木制的）条状滑行装置；（移动重物的）滚杠；滑圈；（航海）滑车吊索；长条饰布，长条地毯；长匐茎，纤匐枝；有长匐茎的植物；蔓生植物，攀缘植物；（热带海洋的）青鲹；回转磨石，上磨盘（=runner stone）"},{"pos":"","trans":"【名】 （Runner）（英）朗纳（人名）"}],"pron":"/ ˈrʌnər /","word":"runner"},{"defs":[{"pos":"n","trans":"一排，一行；（电影院或飞机里的）一排座位；排屋，排房；（用于街道名称）路，街；划船；严重分歧，纠纷；争吵，打斗；叫嚷，吵闹（row的复数）"},{"pos":"v","trans":"划船，划船运送；使……列成一排；争吵，争执（row的第三人称单数）"},{"pos":"n","trans":"（Rows）（美、英、印尼）罗斯（人名）"}],"pron":"/ roz /","word":"rows"},{"defs":[{"pos":"","trans":"执行"}],"pron":"/ ədˈmɪnɪstəd /","word":"administered"},{"defs":[{"pos":"n","trans":"概念，想法；缝纫用品；一时的念头，突发的奇想"}],"pron":"/ ˈnoʊʃ(ə)n /","word":"notion"},{"defs":[{"pos":"abbr","trans":"平方（square）"}],"pron":"/ es ˈkjuː /","word":"sq"},{"defs":[{"pos":"n","trans":"[解剖]皮肤（skin 的复数）；皮囊；（美）连皮烤土豆；面板"},{"pos":"v","trans":"剥皮；植皮（skin 的三单形式）"}],"pron":"/ skɪnz /","word":"skins"},{"defs":[{"pos":"adj","trans":"装甲的；披甲的；有锁子甲状鳞的"},{"pos":"v","trans":"邮寄；使披上铠甲的（mail 的过去式和过去分词）"}],"pron":"/ meɪld /","word":"mailed"},{"defs":[{"pos":"abbr","trans":"检查局（Office of Censorship）；指挥官（Officer Commanding）"}],"word":"oc"},{"defs":[{"pos":"n","trans":"日本富士通公司（全球最大的计算机公司之一）"}],"word":"fujitsu"},{"defs":[{"pos":"n","trans":"拼写，拼写能力；拼法，拼读"},{"pos":"v","trans":"（用字母）拼写，拼出；招致，意味着（通常指坏事）；替换，顶替（spell 的现在分词形式）"},{"pos":"","trans":"【名】 （Spelling）斯佩林（人名）"}],"pron":"/ ˈspelɪŋ /","word":"spelling"},{"defs":[{"pos":"adj","trans":"北极的；严寒的，极冷的"},{"pos":"n","trans":"北极，北极地区；防水套鞋"},{"pos":"","trans":"【名】 （Arctic）（英）阿克蒂克（人名）"}],"pron":"/ ˈɑːrktɪk /","word":"arctic"},{"defs":[{"pos":"n","trans":"考试；检查（exam 的复数）"}],"pron":"/ ɪɡˈzæmz /","word":"exams"},{"defs":[{"pos":"n","trans":"[劳经]奖励；奖品（reward 的复数）"},{"pos":"v","trans":"[劳经]奖赏；酬谢；报答（reward 的单三形式）"}],"pron":"/ rɪ'wɔrdz /","word":"rewards"},{"defs":[{"pos":"prep","trans":"在……下方；在……表面之下，隐藏在……之下；（对某人来说）不够好，不相称；低于，次于"},{"pos":"adv","trans":"在下面，在底下"}],"pron":"/ bɪˈniːθ /","word":"beneath"},{"defs":[{"pos":"v","trans":"使（情感、决心等）更强烈，使（关系）更加紧密；巩固（地位），加强（实力）；（货币）升值；增强（体质）；为……提供更有力的理由（证据）；（风力或水力）变强；使（法令或处罚）更有效；加强，加固（物体或结构）"}],"pron":"/ ˈstreŋθn /","word":"strengthen"},{"defs":[{"pos":"v","trans":"保卫，防御；捍卫，维护；（在比赛中）防守，防卫；参加卫冕赛，蝉联；做……的辩护律师，为……辩解"}],"pron":"/ dɪˈfend /","word":"defend"},{"defs":[{"pos":"n","trans":"合金结（抗干扰）"}],"word":"aj"},{"defs":[{"pos":"n","trans":"弗雷德里克（男子名）"}],"pron":"/ ˈfredrɪk /","word":"frederick"},{"defs":[{"pos":"n","trans":"（美）医疗补助计划"}],"pron":"/ ˈmedɪkeɪd /","word":"medicaid"},{"defs":[{"pos":"","trans":"（=tandem romberg eyes open）罗姆伯格（氏）病的串联性眼开合"}],"word":"treo"},{"defs":[{"pos":"adj","trans":"红外线的；（设备，技术）使用红外的，涉及红外的"},{"pos":"n","trans":"红外区，红外线，红外辐射"}],"pron":"/ ˌɪnfrəˈred /","word":"infrared"},{"defs":[{"pos":"num","trans":"第七"},{"pos":"n","trans":"七分之一；（比赛或竞赛的）第七名；第七（用来引出第七个要点或原因）；（音乐）七度音程，七度和弦"},{"pos":"adj","trans":"第七的；七分之一的"},{"pos":"adv","trans":"居第七位地；第七点（用来引出第七个要点或原因）"},{"pos":"n","trans":"（Seventh）（美、俄、印）塞文特（人名）"}],"pron":"/ ˈsev(ə)nθ /","word":"seventh"},{"defs":[{"pos":"n","trans":"众神，诸神，泛指神灵（god 的复数）；上帝们"}],"pron":"/ ɡɒdz /","word":"gods"},{"defs":[{"pos":"n","trans":"（Une）（瑞）乌内（人名）"}],"pron":"/ ,ju ɛn 'i /","word":"une"},{"defs":[{"pos":"v","trans":"赖账"},{"pos":"adj","trans":"（Welsh）威尔士的；威尔士人的；威尔士语的；威尔士文化的"},{"pos":"n","trans":"（Welsh）威尔士人；威尔士语；威尔士猪"},{"pos":"n","trans":"（Welsh）（美）韦尔什（人名）"}],"pron":"/ welʃ /","word":"welsh"}]